{"desc":"OK","code":200,"extra":"","data":{"cacheIndex":0,"list":[{"no":0,"type":"KEYWORD_BACKGROUND","active":false,"deploy":false,"data":"{\"imageUrl\":\"http://m1.daumcdn.net/thumb/R1280x0/?fname\\u003dhttp://u1.daumcdn.net/brunch/static/img/now/title/27.png\"}","contents":{"imageUrl":"http://m1.daumcdn.net/thumb/R1280x0/?fname=http://u1.daumcdn.net/brunch/static/img/now/title/27.png"},"createTime":null,"seq":0,"setNo":0},{"no":1,"type":"KEYWORD_TOP_TITLE","active":false,"deploy":false,"data":"{\"keywordItemList\":[{\"description\":\"지구한바퀴\\n세계여행\",\"groupType\":\"group\",\"groupNo\":38,\"isPcTopActive\":\"checked\",\"isNew\":\"false\",\"no\":38,\"id\":38,\"score\":0,\"count\":1},{\"description\":\"그림·웹툰\",\"groupType\":\"group\",\"groupNo\":34,\"isPcTopActive\":\"checked\",\"isNew\":\"false\",\"no\":34,\"id\":34,\"score\":0,\"count\":1},{\"description\":\"시사·이슈\",\"groupType\":\"group\",\"groupNo\":67,\"isPcTopActive\":\"checked\",\"isNew\":\"true\",\"no\":67,\"id\":67,\"score\":0,\"count\":1},{\"description\":\"IT\\n트렌드\",\"groupType\":\"group\",\"groupNo\":33,\"isPcTopActive\":\"checked\",\"isNew\":\"false\",\"no\":33,\"id\":33,\"score\":0,\"count\":1},{\"description\":\"사진·촬영\",\"groupType\":\"group\",\"groupNo\":39,\"isPcTopActive\":\"checked\",\"no\":39,\"id\":39,\"score\":0,\"count\":1},{\"description\":\"취향저격\\n영화 리뷰\",\"groupType\":\"group\",\"groupNo\":32,\"isPcTopActive\":\"checked\",\"no\":32,\"id\":32,\"score\":0,\"count\":1},{\"description\":\"오늘은\\n이런 책\",\"groupType\":\"group\",\"groupNo\":40,\"isPcTopActive\":\"checked\",\"isNew\":\"true\",\"no\":40,\"id\":40,\"score\":0,\"count\":1},{\"description\":\"뮤직\\n인사이드\",\"groupType\":\"group\",\"groupNo\":41,\"isPcTopActive\":\"checked\",\"no\":41,\"id\":41,\"score\":0,\"count\":1},{\"description\":\"글쓰기\\n코치\",\"groupType\":\"group\",\"groupNo\":2,\"isPcTopActive\":\"checked\",\"isNew\":\"false\",\"no\":2,\"id\":2,\"score\":0,\"count\":1},{\"description\":\"직장인\\n현실 조언\",\"groupType\":\"group\",\"groupNo\":9,\"isPcTopActive\":\"checked\",\"isNew\":\"false\",\"no\":9,\"id\":9,\"score\":0,\"count\":1},{\"description\":\"스타트업\\n경험담\",\"groupType\":\"group\",\"groupNo\":35,\"isPcTopActive\":\"checked\",\"isNew\":\"true\",\"no\":35,\"id\":35,\"score\":0,\"count\":1},{\"description\":\"육아\\n이야기\",\"groupType\":\"group\",\"groupNo\":59,\"isPcTopActive\":\"checked\",\"no\":59,\"id\":59,\"score\":0,\"count\":1},{\"description\":\"요리·레시피\",\"groupType\":\"group\",\"groupNo\":87,\"isPcTopActive\":\"checked\",\"no\":87,\"id\":87,\"score\":0,\"count\":1},{\"description\":\"건강·운동\",\"groupType\":\"group\",\"groupNo\":45,\"isPcTopActive\":\"checked\",\"isNew\":\"false\",\"no\":45,\"id\":45,\"score\":0,\"count\":1},{\"description\":\"멘탈 관리\\n심리 탐구\",\"groupType\":\"group\",\"groupNo\":42,\"isPcTopActive\":\"checked\",\"no\":42,\"id\":42,\"score\":0,\"count\":1},{\"description\":\"디자인\\n스토리\",\"groupType\":\"group\",\"groupNo\":43,\"isPcTopActive\":\"checked\",\"isNew\":\"false\",\"no\":43,\"id\":43,\"score\":0,\"count\":1},{\"description\":\"글로 읽는\\n미술\",\"groupType\":\"group\",\"groupNo\":63,\"isPcTopActive\":\"\",\"isNew\":\"false\",\"no\":63,\"id\":63,\"score\":0,\"count\":1},{\"description\":\"문화·예술\",\"groupType\":\"group\",\"groupNo\":64,\"isPcTopActive\":\"checked\",\"isNew\":\"false\",\"no\":64,\"id\":64,\"score\":0,\"count\":1},{\"description\":\"건축·설계\",\"groupType\":\"group\",\"groupNo\":77,\"isPcTopActive\":\"checked\",\"isNew\":\"false\",\"no\":77,\"id\":77,\"score\":0,\"count\":1},{\"description\":\"인문학·철학\",\"groupType\":\"group\",\"groupNo\":52,\"isPcTopActive\":\"checked\",\"isNew\":\"false\",\"no\":52,\"id\":52,\"score\":0,\"count\":1},{\"description\":\"쉽게 읽는\\n역사\",\"groupType\":\"group\",\"groupNo\":69,\"isPcTopActive\":\"checked\",\"no\":69,\"id\":69,\"score\":0,\"count\":1},{\"description\":\"우리집\\n반려동물\",\"groupType\":\"group\",\"groupNo\":1,\"isPcTopActive\":\"checked\",\"no\":1,\"id\":1,\"score\":0,\"count\":1},{\"description\":\"멋진\\n캘리그래피\",\"groupType\":\"group\",\"groupNo\":56,\"isPcTopActive\":\"checked\",\"no\":56,\"id\":56,\"score\":0,\"count\":1},{\"description\":\"사랑·이별\",\"groupType\":\"group\",\"groupNo\":44,\"isPcTopActive\":\"checked\",\"isNew\":\"false\",\"no\":44,\"id\":44,\"score\":0,\"count\":1},{\"description\":\"감성\\n에세이\",\"groupType\":\"group\",\"groupNo\":46,\"isPcTopActive\":\"checked\",\"isNew\":\"true\",\"no\":46,\"id\":46,\"score\":0,\"count\":1}]}","contents":{"keywordItemList":[{"no":38,"id":38,"onoff":null,"keyword":null,"type":null,"score":0,"updateTime":null,"createTime":null,"source":null,"agentId":null,"bannerOnoff":null,"pcImageUrl":null,"pcImageLink":null,"pcBackgroundColor":null,"pcTextImage":null,"mobileImageUrl":null,"mobileImageLink":null,"mobileBackgroundColor":null,"mobileTextImage":null,"selected":null,"count":1,"orderType":null,"description":"지구한바퀴\n세계여행","groupType":"group","groupNo":38,"groupCondition":null,"isPcTopActive":"checked","isNew":"false","finalScore":0.0},{"no":34,"id":34,"onoff":null,"keyword":null,"type":null,"score":0,"updateTime":null,"createTime":null,"source":null,"agentId":null,"bannerOnoff":null,"pcImageUrl":null,"pcImageLink":null,"pcBackgroundColor":null,"pcTextImage":null,"mobileImageUrl":null,"mobileImageLink":null,"mobileBackgroundColor":null,"mobileTextImage":null,"selected":null,"count":1,"orderType":null,"description":"그림·웹툰","groupType":"group","groupNo":34,"groupCondition":null,"isPcTopActive":"checked","isNew":"false","finalScore":0.0},{"no":67,"id":67,"onoff":null,"keyword":null,"type":null,"score":0,"updateTime":null,"createTime":null,"source":null,"agentId":null,"bannerOnoff":null,"pcImageUrl":null,"pcImageLink":null,"pcBackgroundColor":null,"pcTextImage":null,"mobileImageUrl":null,"mobileImageLink":null,"mobileBackgroundColor":null,"mobileTextImage":null,"selected":null,"count":1,"orderType":null,"description":"시사·이슈","groupType":"group","groupNo":67,"groupCondition":null,"isPcTopActive":"checked","isNew":"true","finalScore":0.0},{"no":33,"id":33,"onoff":null,"keyword":null,"type":null,"score":0,"updateTime":null,"createTime":null,"source":null,"agentId":null,"bannerOnoff":null,"pcImageUrl":null,"pcImageLink":null,"pcBackgroundColor":null,"pcTextImage":null,"mobileImageUrl":null,"mobileImageLink":null,"mobileBackgroundColor":null,"mobileTextImage":null,"selected":null,"count":1,"orderType":null,"description":"IT\n트렌드","groupType":"group","groupNo":33,"groupCondition":null,"isPcTopActive":"checked","isNew":"false","finalScore":0.0},{"no":39,"id":39,"onoff":null,"keyword":null,"type":null,"score":0,"updateTime":null,"createTime":null,"source":null,"agentId":null,"bannerOnoff":null,"pcImageUrl":null,"pcImageLink":null,"pcBackgroundColor":null,"pcTextImage":null,"mobileImageUrl":null,"mobileImageLink":null,"mobileBackgroundColor":null,"mobileTextImage":null,"selected":null,"count":1,"orderType":null,"description":"사진·촬영","groupType":"group","groupNo":39,"groupCondition":null,"isPcTopActive":"checked","isNew":null,"finalScore":0.0},{"no":32,"id":32,"onoff":null,"keyword":null,"type":null,"score":0,"updateTime":null,"createTime":null,"source":null,"agentId":null,"bannerOnoff":null,"pcImageUrl":null,"pcImageLink":null,"pcBackgroundColor":null,"pcTextImage":null,"mobileImageUrl":null,"mobileImageLink":null,"mobileBackgroundColor":null,"mobileTextImage":null,"selected":null,"count":1,"orderType":null,"description":"취향저격\n영화 리뷰","groupType":"group","groupNo":32,"groupCondition":null,"isPcTopActive":"checked","isNew":null,"finalScore":0.0},{"no":40,"id":40,"onoff":null,"keyword":null,"type":null,"score":0,"updateTime":null,"createTime":null,"source":null,"agentId":null,"bannerOnoff":null,"pcImageUrl":null,"pcImageLink":null,"pcBackgroundColor":null,"pcTextImage":null,"mobileImageUrl":null,"mobileImageLink":null,"mobileBackgroundColor":null,"mobileTextImage":null,"selected":null,"count":1,"orderType":null,"description":"오늘은\n이런 책","groupType":"group","groupNo":40,"groupCondition":null,"isPcTopActive":"checked","isNew":"true","finalScore":0.0},{"no":41,"id":41,"onoff":null,"keyword":null,"type":null,"score":0,"updateTime":null,"createTime":null,"source":null,"agentId":null,"bannerOnoff":null,"pcImageUrl":null,"pcImageLink":null,"pcBackgroundColor":null,"pcTextImage":null,"mobileImageUrl":null,"mobileImageLink":null,"mobileBackgroundColor":null,"mobileTextImage":null,"selected":null,"count":1,"orderType":null,"description":"뮤직\n인사이드","groupType":"group","groupNo":41,"groupCondition":null,"isPcTopActive":"checked","isNew":null,"finalScore":0.0},{"no":2,"id":2,"onoff":null,"keyword":null,"type":null,"score":0,"updateTime":null,"createTime":null,"source":null,"agentId":null,"bannerOnoff":null,"pcImageUrl":null,"pcImageLink":null,"pcBackgroundColor":null,"pcTextImage":null,"mobileImageUrl":null,"mobileImageLink":null,"mobileBackgroundColor":null,"mobileTextImage":null,"selected":null,"count":1,"orderType":null,"description":"글쓰기\n코치","groupType":"group","groupNo":2,"groupCondition":null,"isPcTopActive":"checked","isNew":"false","finalScore":0.0},{"no":9,"id":9,"onoff":null,"keyword":null,"type":null,"score":0,"updateTime":null,"createTime":null,"source":null,"agentId":null,"bannerOnoff":null,"pcImageUrl":null,"pcImageLink":null,"pcBackgroundColor":null,"pcTextImage":null,"mobileImageUrl":null,"mobileImageLink":null,"mobileBackgroundColor":null,"mobileTextImage":null,"selected":null,"count":1,"orderType":null,"description":"직장인\n현실 조언","groupType":"group","groupNo":9,"groupCondition":null,"isPcTopActive":"checked","isNew":"false","finalScore":0.0},{"no":35,"id":35,"onoff":null,"keyword":null,"type":null,"score":0,"updateTime":null,"createTime":null,"source":null,"agentId":null,"bannerOnoff":null,"pcImageUrl":null,"pcImageLink":null,"pcBackgroundColor":null,"pcTextImage":null,"mobileImageUrl":null,"mobileImageLink":null,"mobileBackgroundColor":null,"mobileTextImage":null,"selected":null,"count":1,"orderType":null,"description":"스타트업\n경험담","groupType":"group","groupNo":35,"groupCondition":null,"isPcTopActive":"checked","isNew":"true","finalScore":0.0},{"no":59,"id":59,"onoff":null,"keyword":null,"type":null,"score":0,"updateTime":null,"createTime":null,"source":null,"agentId":null,"bannerOnoff":null,"pcImageUrl":null,"pcImageLink":null,"pcBackgroundColor":null,"pcTextImage":null,"mobileImageUrl":null,"mobileImageLink":null,"mobileBackgroundColor":null,"mobileTextImage":null,"selected":null,"count":1,"orderType":null,"description":"육아\n이야기","groupType":"group","groupNo":59,"groupCondition":null,"isPcTopActive":"checked","isNew":null,"finalScore":0.0},{"no":87,"id":87,"onoff":null,"keyword":null,"type":null,"score":0,"updateTime":null,"createTime":null,"source":null,"agentId":null,"bannerOnoff":null,"pcImageUrl":null,"pcImageLink":null,"pcBackgroundColor":null,"pcTextImage":null,"mobileImageUrl":null,"mobileImageLink":null,"mobileBackgroundColor":null,"mobileTextImage":null,"selected":null,"count":1,"orderType":null,"description":"요리·레시피","groupType":"group","groupNo":87,"groupCondition":null,"isPcTopActive":"checked","isNew":null,"finalScore":0.0},{"no":45,"id":45,"onoff":null,"keyword":null,"type":null,"score":0,"updateTime":null,"createTime":null,"source":null,"agentId":null,"bannerOnoff":null,"pcImageUrl":null,"pcImageLink":null,"pcBackgroundColor":null,"pcTextImage":null,"mobileImageUrl":null,"mobileImageLink":null,"mobileBackgroundColor":null,"mobileTextImage":null,"selected":null,"count":1,"orderType":null,"description":"건강·운동","groupType":"group","groupNo":45,"groupCondition":null,"isPcTopActive":"checked","isNew":"false","finalScore":0.0},{"no":42,"id":42,"onoff":null,"keyword":null,"type":null,"score":0,"updateTime":null,"createTime":null,"source":null,"agentId":null,"bannerOnoff":null,"pcImageUrl":null,"pcImageLink":null,"pcBackgroundColor":null,"pcTextImage":null,"mobileImageUrl":null,"mobileImageLink":null,"mobileBackgroundColor":null,"mobileTextImage":null,"selected":null,"count":1,"orderType":null,"description":"멘탈 관리\n심리 탐구","groupType":"group","groupNo":42,"groupCondition":null,"isPcTopActive":"checked","isNew":null,"finalScore":0.0},{"no":43,"id":43,"onoff":null,"keyword":null,"type":null,"score":0,"updateTime":null,"createTime":null,"source":null,"agentId":null,"bannerOnoff":null,"pcImageUrl":null,"pcImageLink":null,"pcBackgroundColor":null,"pcTextImage":null,"mobileImageUrl":null,"mobileImageLink":null,"mobileBackgroundColor":null,"mobileTextImage":null,"selected":null,"count":1,"orderType":null,"description":"디자인\n스토리","groupType":"group","groupNo":43,"groupCondition":null,"isPcTopActive":"checked","isNew":"false","finalScore":0.0},{"no":63,"id":63,"onoff":null,"keyword":null,"type":null,"score":0,"updateTime":null,"createTime":null,"source":null,"agentId":null,"bannerOnoff":null,"pcImageUrl":null,"pcImageLink":null,"pcBackgroundColor":null,"pcTextImage":null,"mobileImageUrl":null,"mobileImageLink":null,"mobileBackgroundColor":null,"mobileTextImage":null,"selected":null,"count":1,"orderType":null,"description":"글로 읽는\n미술","groupType":"group","groupNo":63,"groupCondition":null,"isPcTopActive":"","isNew":"false","finalScore":0.0},{"no":64,"id":64,"onoff":null,"keyword":null,"type":null,"score":0,"updateTime":null,"createTime":null,"source":null,"agentId":null,"bannerOnoff":null,"pcImageUrl":null,"pcImageLink":null,"pcBackgroundColor":null,"pcTextImage":null,"mobileImageUrl":null,"mobileImageLink":null,"mobileBackgroundColor":null,"mobileTextImage":null,"selected":null,"count":1,"orderType":null,"description":"문화·예술","groupType":"group","groupNo":64,"groupCondition":null,"isPcTopActive":"checked","isNew":"false","finalScore":0.0},{"no":77,"id":77,"onoff":null,"keyword":null,"type":null,"score":0,"updateTime":null,"createTime":null,"source":null,"agentId":null,"bannerOnoff":null,"pcImageUrl":null,"pcImageLink":null,"pcBackgroundColor":null,"pcTextImage":null,"mobileImageUrl":null,"mobileImageLink":null,"mobileBackgroundColor":null,"mobileTextImage":null,"selected":null,"count":1,"orderType":null,"description":"건축·설계","groupType":"group","groupNo":77,"groupCondition":null,"isPcTopActive":"checked","isNew":"false","finalScore":0.0},{"no":52,"id":52,"onoff":null,"keyword":null,"type":null,"score":0,"updateTime":null,"createTime":null,"source":null,"agentId":null,"bannerOnoff":null,"pcImageUrl":null,"pcImageLink":null,"pcBackgroundColor":null,"pcTextImage":null,"mobileImageUrl":null,"mobileImageLink":null,"mobileBackgroundColor":null,"mobileTextImage":null,"selected":null,"count":1,"orderType":null,"description":"인문학·철학","groupType":"group","groupNo":52,"groupCondition":null,"isPcTopActive":"checked","isNew":"false","finalScore":0.0},{"no":69,"id":69,"onoff":null,"keyword":null,"type":null,"score":0,"updateTime":null,"createTime":null,"source":null,"agentId":null,"bannerOnoff":null,"pcImageUrl":null,"pcImageLink":null,"pcBackgroundColor":null,"pcTextImage":null,"mobileImageUrl":null,"mobileImageLink":null,"mobileBackgroundColor":null,"mobileTextImage":null,"selected":null,"count":1,"orderType":null,"description":"쉽게 읽는\n역사","groupType":"group","groupNo":69,"groupCondition":null,"isPcTopActive":"checked","isNew":null,"finalScore":0.0},{"no":1,"id":1,"onoff":null,"keyword":null,"type":null,"score":0,"updateTime":null,"createTime":null,"source":null,"agentId":null,"bannerOnoff":null,"pcImageUrl":null,"pcImageLink":null,"pcBackgroundColor":null,"pcTextImage":null,"mobileImageUrl":null,"mobileImageLink":null,"mobileBackgroundColor":null,"mobileTextImage":null,"selected":null,"count":1,"orderType":null,"description":"우리집\n반려동물","groupType":"group","groupNo":1,"groupCondition":null,"isPcTopActive":"checked","isNew":null,"finalScore":0.0},{"no":56,"id":56,"onoff":null,"keyword":null,"type":null,"score":0,"updateTime":null,"createTime":null,"source":null,"agentId":null,"bannerOnoff":null,"pcImageUrl":null,"pcImageLink":null,"pcBackgroundColor":null,"pcTextImage":null,"mobileImageUrl":null,"mobileImageLink":null,"mobileBackgroundColor":null,"mobileTextImage":null,"selected":null,"count":1,"orderType":null,"description":"멋진\n캘리그래피","groupType":"group","groupNo":56,"groupCondition":null,"isPcTopActive":"checked","isNew":null,"finalScore":0.0},{"no":44,"id":44,"onoff":null,"keyword":null,"type":null,"score":0,"updateTime":null,"createTime":null,"source":null,"agentId":null,"bannerOnoff":null,"pcImageUrl":null,"pcImageLink":null,"pcBackgroundColor":null,"pcTextImage":null,"mobileImageUrl":null,"mobileImageLink":null,"mobileBackgroundColor":null,"mobileTextImage":null,"selected":null,"count":1,"orderType":null,"description":"사랑·이별","groupType":"group","groupNo":44,"groupCondition":null,"isPcTopActive":"checked","isNew":"false","finalScore":0.0},{"no":46,"id":46,"onoff":null,"keyword":null,"type":null,"score":0,"updateTime":null,"createTime":null,"source":null,"agentId":null,"bannerOnoff":null,"pcImageUrl":null,"pcImageLink":null,"pcBackgroundColor":null,"pcTextImage":null,"mobileImageUrl":null,"mobileImageLink":null,"mobileBackgroundColor":null,"mobileTextImage":null,"selected":null,"count":1,"orderType":null,"description":"감성\n에세이","groupType":"group","groupNo":46,"groupCondition":null,"isPcTopActive":"checked","isNew":"true","finalScore":0.0}]},"createTime":null,"seq":1,"setNo":0},{"no":3515,"type":"KEYWORD_ARTICLE_AUTO","active":false,"deploy":false,"data":"{\"htmlKeywordTitle\":\"\\u003cb\\u003e애니메이션\\u003c/b\\u003e·\\u003cb\\u003e만화\\u003c/b\\u003e\",\"keywordTitle\":\"애니메이션·만화\",\"groupNo\":76,\"groupType\":\"group\",\"list\":[]}","contents":{"keyword":null,"htmlKeywordTitle":"<b>애니메이션</b>·<b>만화</b>","keywordTitle":"애니메이션·만화","moreLink":null,"groupNo":76,"groupType":"group","list":[]},"createTime":null,"seq":2,"setNo":0},{"no":3516,"type":"KEYWORD_ARTICLE_AUTO","active":false,"deploy":false,"data":"{\"htmlKeywordTitle\":\"멋진 \\u003cb\\u003e캘리그래피\\u003c/b\\u003e\",\"keywordTitle\":\"멋진 캘리그래피\",\"groupNo\":56,\"groupType\":\"group\",\"list\":[]}","contents":{"keyword":null,"htmlKeywordTitle":"멋진 <b>캘리그래피</b>","keywordTitle":"멋진 캘리그래피","moreLink":null,"groupNo":56,"groupType":"group","list":[]},"createTime":null,"seq":3,"setNo":0},{"no":3517,"type":"KEYWORD_ARTICLE_POPULAR","active":false,"deploy":false,"data":null,"contents":null,"createTime":null,"seq":4,"setNo":0},{"no":3519,"type":"KEYWORD_ARTICLE_AUTO","active":false,"deploy":false,"data":"{\"htmlKeywordTitle\":\"취향저격 \\u003cb\\u003e영화\\u003c/b\\u003e 리뷰\",\"keywordTitle\":\"취향저격 영화 리뷰\",\"groupNo\":32,\"groupType\":\"group\",\"list\":[]}","contents":{"keyword":null,"htmlKeywordTitle":"취향저격 <b>영화</b> 리뷰","keywordTitle":"취향저격 영화 리뷰","moreLink":null,"groupNo":32,"groupType":"group","list":[]},"createTime":null,"seq":6,"setNo":0},{"no":3520,"type":"KEYWORD_USER","active":false,"deploy":false,"data":"{\"profileList\":[{\"userId\":\"kEJ\",\"userName\":\"공인식\",\"userImage\":\"http://t1.daumcdn.net/brunch/service/user/kEJ/image/FX9j4b1ID4QSWILcJMOGct1OAcQ.jpeg\",\"profileId\":\"alwayswithya\",\"description\":\"Everything is a test.\",\"createTime\":\"Aug 26, 2015 11:17:10 AM\",\"status\":\"verify\",\"articleCount\":53,\"socialUser\":false,\"writerCount\":52,\"followerCount\":55},{\"userId\":\"tlV\",\"userName\":\"언이\",\"userImage\":\"http://t1.daumcdn.net/brunch/service/user/tlV/image/6KmptzJ7-Bh_CkRVFl3z3epoooM\",\"profileId\":\"zkwmfk\",\"description\":\"언이의 브런치 입니다\",\"createTime\":\"Sep 16, 2015 9:47:25 PM\",\"status\":\"verify\",\"articleCount\":103,\"socialUser\":false,\"writerCount\":108,\"followerCount\":109},{\"userId\":\"suk\",\"userName\":\"badac\",\"userImage\":\"http://t1.daumcdn.net/brunch/service/guest/image/A4-6Hd9XNmSlYX--kcYGByFo7Y0.png\",\"profileId\":\"slowbadac\",\"description\":\"새내기 귀촌인.\\n자급지향 시골독립 생활인.\",\"createTime\":\"Sep 14, 2015 8:31:43 PM\",\"status\":\"verify\",\"articleCount\":35,\"socialUser\":false,\"writerCount\":5,\"followerCount\":1434},{\"userId\":\"mGD\",\"userName\":\"summer\",\"userImage\":\"http://t1.daumcdn.net/brunch/service/user/mGD/image/xTYjZiT3alH0dN1VQWrwXHXPdhY\",\"profileId\":\"summ-er\",\"description\":\"너무도 소중한 일상의 평화\",\"createTime\":\"Aug 31, 2015 9:43:57 AM\",\"status\":\"verify\",\"articleCount\":55,\"socialUser\":false,\"writerCount\":14,\"followerCount\":170},{\"userId\":\"t48\",\"userName\":\"황길환\",\"userImage\":\"http://t1.daumcdn.net/brunch/service/user/t48/image/pCs76b8nrNZ2Q67wXk8Kh6os0ew.png\",\"profileId\":\"brunchxjk0\",\"description\":\"언론정보학과에서 Human-Computer Interaction을 공부하는 대학원생입니다. 인공지능과 대화에 관심이 많습니다. :)\",\"createTime\":\"Sep 16, 2015 10:56:47 AM\",\"status\":\"verify\",\"articleCount\":22,\"socialUser\":false,\"writerCount\":40,\"followerCount\":281},{\"userId\":\"loV\",\"userName\":\"graysbook\",\"userImage\":\"http://t1.daumcdn.net/brunch/service/guest/image/mN1-vvbrW3e4UHuPfERKoJJbFxY.png\",\"profileId\":\"graysbook\",\"description\":\"마들렌\",\"createTime\":\"Aug 28, 2015 1:39:29 AM\",\"status\":\"verify\",\"articleCount\":25,\"socialUser\":false,\"writerCount\":24,\"followerCount\":219},{\"userId\":\"b15\",\"userName\":\"윤군\",\"userImage\":\"http://t1.daumcdn.net/brunch/service/user/b15/image/lfiSOkoEtGyPEUeJ31IvjHxL9S4\",\"profileId\":\"yunjihoon\",\"description\":\"타로카드를 읽고\\n사랑 앞에서 이별을 씁니다\",\"createTime\":\"Jul 24, 2015 8:55:59 AM\",\"status\":\"verify\",\"articleCount\":247,\"socialUser\":false,\"writerCount\":165,\"followerCount\":1999},{\"userId\":\"QHD\",\"userName\":\"새벽 세시\",\"userImage\":\"http://t1.daumcdn.net/brunch/service/guest/image/rjhQS7dxEdA7PphKnNJsfRBL0QE.png\",\"profileId\":\"jay8zg0\",\"description\":\"당신의 새벽 세시.\\n\\nwww.facebook.com/yours3am\",\"createTime\":\"Nov 25, 2015 4:50:05 AM\",\"status\":\"verify\",\"articleCount\":200,\"socialUser\":false,\"writerCount\":0,\"followerCount\":5189},{\"userId\":\"6Hi\",\"userName\":\"Hong Sukwoo\",\"userImage\":\"http://t1.daumcdn.net/brunch/service/guest/image/j0IlNUt1rl1wmXuD8Mh7ljlb1wU\",\"profileId\":\"yourboyhood\",\"description\":\"Fashion journalist and essayist.\\n\\u003cThe NAVY Magazine\\u003e 에디터, @TheNAVYLab 디렉터.\",\"createTime\":\"Jul 5, 2015 4:46:08 PM\",\"status\":\"verify\",\"articleCount\":138,\"socialUser\":false,\"writerCount\":0,\"followerCount\":1179},{\"userId\":\"23F6\",\"userName\":\"씨앤우즈\",\"userImage\":\"http://t1.daumcdn.net/brunch/service/guest/image/Ev3jt2LEVbrUxkGG-hYcaOjhcIk.png\",\"profileId\":\"heat0508\",\"description\":\"어느날 꿈에서 깨었다. 물에서 나온 사람처럼 발아래 꿈의 잔해들이 뚝뚝 떨어졌다. 그렇게 바닥에 그려진 무늬들을 글로 옮기기 시작했다.\",\"createTime\":\"Jun 12, 2016 8:45:54 PM\",\"status\":\"verify\",\"articleCount\":56,\"socialUser\":false,\"writerCount\":1,\"followerCount\":1208},{\"userId\":\"Qcl\",\"userName\":\"아흔아홉\",\"userImage\":\"http://t1.daumcdn.net/brunch/service/user/Qcl/image/wFRK7xzrzVfzKY5MNzVihZt9Ph0.jpg\",\"profileId\":\"hola99\",\"description\":\"그림쟁이\",\"createTime\":\"Nov 23, 2015 2:44:52 AM\",\"status\":\"verify\",\"articleCount\":17,\"socialUser\":false,\"writerCount\":3,\"followerCount\":923},{\"userId\":\"1WRs\",\"userName\":\"민트코끼리\",\"userImage\":\"http://t1.daumcdn.net/brunch/service/user/1WRs/image/GeVN9IMoonsQbxYUOUgaTgIXRMI.jpeg\",\"profileId\":\"mintelephant\",\"description\":\"말 못했던 시절의 기억, 일상의 기록 ,\\n 필름 편지를 쓰는 치과의사\",\"createTime\":\"May 12, 2016 6:05:17 PM\",\"status\":\"verify\",\"articleCount\":54,\"socialUser\":false,\"writerCount\":14,\"followerCount\":170},{\"userId\":\"2kMn\",\"userName\":\"Lion Kid\",\"userImage\":\"http://t1.daumcdn.net/brunch/service/user/2kMn/image/h-y6YVXTSgPpq6HUdlj8ZM_8X4Q.png\",\"profileId\":\"basenell\",\"description\":\"잡다하지만, 방대하지는 못한 관심사.\\nintherainglow@gmail.com\",\"createTime\":\"Aug 24, 2016 7:29:29 PM\",\"status\":\"verify\",\"articleCount\":160,\"socialUser\":false,\"writerCount\":1,\"followerCount\":1461},{\"userId\":\"1lRv\",\"userName\":\"네오소울\",\"userImage\":\"http://t1.daumcdn.net/brunch/service/user/1lRv/image/Ibs5ZfV0jvnhdoW8hfEKwluxX-I.jpg\",\"profileId\":\"artnsoul\",\"description\":\"진정한 의미의 관람객으로서의 글쓰기\\n듣고 보고 읽기를 통해 그려보는 마음의 파동.\",\"createTime\":\"Mar 18, 2016 2:12:22 PM\",\"status\":\"verify\",\"articleCount\":30,\"socialUser\":false,\"writerCount\":38,\"followerCount\":291},{\"userId\":\"260l\",\"userName\":\"cirin\",\"userImage\":\"http://t1.daumcdn.net/brunch/service/user/260l/image/Rb5yIUwbzz8F_fVlivzluRs4pxc.png\",\"profileId\":\"cirin\",\"description\":\"어떤 문장들은 그림처럼 남는다.\",\"createTime\":\"Jun 24, 2016 4:53:32 PM\",\"status\":\"verify\",\"articleCount\":125,\"socialUser\":false,\"writerCount\":1,\"followerCount\":1545},{\"userId\":\"3w4D\",\"userName\":\"김수현\",\"userImage\":\"http://t1.daumcdn.net/brunch/service/guest/image/Y6S4GfVUWhYFaHDHk2Isb9CCSls\",\"profileId\":\"ipretty0217\",\"description\":\"\\u003c나는 나로 살기로 했다\\u003e 작가 김수현입니다.\",\"createTime\":\"May 8, 2017 2:44:15 PM\",\"status\":\"verify\",\"articleCount\":5,\"socialUser\":false,\"writerCount\":1,\"followerCount\":1080},{\"userId\":\"7vx\",\"userName\":\"Ossian\",\"userImage\":\"http://t1.daumcdn.net/brunch/service/user/7vx/image/5F03vl2q6HS4wvNzCFvNYNyXNcA\",\"profileId\":\"ossian\",\"description\":\"꿈을 꾸며 글을 쓰고, \\n글을 쓰며 꿈을 꿉니다.\",\"createTime\":\"Jul 8, 2015 2:16:29 PM\",\"status\":\"verify\",\"articleCount\":104,\"socialUser\":false,\"writerCount\":96,\"followerCount\":2816},{\"userId\":\"3aCS\",\"userName\":\"장연정\",\"userImage\":\"http://t1.daumcdn.net/brunch/service/user/3aCS/image/W8-mBXX5wzIh7l1N3WS-stpdPf8.jpg\",\"profileId\":\"jazzstream\",\"description\":\"긴 글, 때때로 짧은 노랫말을 씁니다.\",\"createTime\":\"Mar 2, 2017 10:20:49 PM\",\"status\":\"verify\",\"articleCount\":9,\"socialUser\":false,\"writerCount\":1,\"followerCount\":99},{\"userId\":\"3kpG\",\"userName\":\"김수민\",\"userImage\":\"http://t1.daumcdn.net/brunch/service/guest/image/c5Cfx6BZt9cMCbRNoVEb1altvck\",\"profileId\":\"writersumin\",\"description\":\"한 사람을 잃고 한 페이지를 채워가는 작가 김수민입니다. 어떤 말로도 위로가 안 되는 당신이 부디 위로가 되기를.\",\"createTime\":\"Mar 31, 2017 5:42:06 PM\",\"status\":\"verify\",\"articleCount\":5,\"socialUser\":false,\"writerCount\":1,\"followerCount\":501},{\"userId\":\"r5H\",\"userName\":\"홍환\",\"userImage\":\"http://t1.daumcdn.net/brunch/service/guest/image/WCOgIfFR6GHDtgyk10wkgKEfDyU\",\"profileId\":\"kyangkyang\",\"description\":\"일상관찰자\",\"createTime\":\"Sep 10, 2015 5:33:13 PM\",\"status\":\"verify\",\"articleCount\":131,\"socialUser\":false,\"writerCount\":63,\"followerCount\":259},{\"userId\":\"1gtW\",\"userName\":\"Jua\",\"userImage\":\"http://t1.daumcdn.net/brunch/service/user/1gtW/image/DLxzyna28uR62_1OF49rjmxqw2U.jpg\",\"profileId\":\"juabae\",\"description\":\"나를 찾고 동시에 버리는 여행을 한다. 거리에서 사람과 삶의 아름다움을 발견하고 찍는다. 마음이 담긴 글을 통해 누군가에게 위로가 되길 소망한다.\\ninstagram@jua_bae\",\"createTime\":\"Feb 27, 2016 8:58:21 PM\",\"status\":\"verify\",\"articleCount\":33,\"socialUser\":false,\"writerCount\":20,\"followerCount\":1481},{\"userId\":\"91x\",\"userName\":\"Yoona Kim\",\"userImage\":\"http://t1.daumcdn.net/brunch/service/user/91x/image/XTP01aK6gXYtQh_8vf_NkCeXQWQ.jpg\",\"profileId\":\"intlovesong\",\"description\":\"작가 #색에미친청춘\\nynkimj@gmail.com\",\"createTime\":\"Jul 15, 2015 12:18:43 PM\",\"status\":\"verify\",\"articleCount\":52,\"socialUser\":false,\"writerCount\":32,\"followerCount\":1695},{\"userId\":\"1ar6\",\"userName\":\"김덕영\",\"userImage\":\"http://t1.daumcdn.net/brunch/service/guest/image/HvbOUDaQX9HoqtENXioFagIxGSw.jpg\",\"profileId\":\"altna84\",\"description\":\"다큐멘터리를 제작하다 이제는 글쓰는 작가로 변신 중입니다. 서촌의 작은 골목길 까페, \\u0027김PD의 통의동 스토리\\u0027에서 조금은 색다른 방식으로 창작을 하면서 사람들과 만나고 있습니다.\",\"createTime\":\"Feb 4, 2016 6:43:39 PM\",\"status\":\"verify\",\"articleCount\":89,\"socialUser\":false,\"writerCount\":10,\"followerCount\":4209},{\"userId\":\"szK\",\"userName\":\"살찐 병아리\",\"userImage\":\"http://t1.daumcdn.net/brunch/service/user/szK/image/vVKMaXFbfX72TGheLucfaxb4zHw.jpg\",\"profileId\":\"keh7890\",\"description\":\"공감되는 토탁토닥 이야기\",\"createTime\":\"Sep 15, 2015 1:37:47 AM\",\"status\":\"verify\",\"articleCount\":85,\"socialUser\":false,\"writerCount\":7,\"followerCount\":2205},{\"userId\":\"oK4\",\"userName\":\"장작가\",\"userImage\":\"http://t1.daumcdn.net/brunch/service/user/oK4/image/tUFfMYI4xQng8qABQvOWAu6inwM.JPG\",\"profileId\":\"yogurtradio\",\"description\":\"전 다큐멘터리 방송작가\\n사랑, 증오, 상처, 위로 등.\\n우리가 사는 세상을 담담하게 이야기하는 곳. [이메일] yogurtradio@naver.com\",\"createTime\":\"Sep 4, 2015 10:08:08 PM\",\"status\":\"verify\",\"articleCount\":78,\"socialUser\":false,\"writerCount\":7,\"followerCount\":1238},{\"userId\":\"7KD\",\"userName\":\"남시언\",\"userImage\":\"http://t1.daumcdn.net/brunch/service/user/7KD/image/Ye1GoUvRynIvoWoDQa7xRbQO5EU.JPG\",\"profileId\":\"namsieon\",\"description\":\"창조적 꼴통, 작가,  \\u003c1인분 청춘\\u003e \\u003c인생을 바꾸는 기적의 블로그\\u003e \\u003c아름다운 사표\\u003e의 저자, 취미는 멍 때리기, me@namsieon.com\",\"createTime\":\"Jul 9, 2015 11:59:03 AM\",\"status\":\"verify\",\"articleCount\":87,\"socialUser\":false,\"writerCount\":5,\"followerCount\":1797},{\"userId\":\"11PJ\",\"userName\":\"김도경\",\"userImage\":\"http://t1.daumcdn.net/brunch/service/user/11PJ/image/Z_TjTxN11hsle5POp1a-WmkjBs0.jpg\",\"profileId\":\"this7day\",\"description\":\"그림에세이,웹툰,캐리커쳐,캘리그라피를 만드는 김도경의 브런치입니다.\\ndreampen@naver.com\",\"createTime\":\"Jan 3, 2016 1:00:32 AM\",\"status\":\"verify\",\"articleCount\":41,\"socialUser\":false,\"writerCount\":8,\"followerCount\":2146},{\"userId\":\"yfq\",\"userName\":\"그럼에도 불구하고\",\"userImage\":\"http://t1.daumcdn.net/brunch/service/user/yfq/image/TxUHSYmzLdBuPKhGsLQcPF3ZuVE\",\"profileId\":\"shoostory\",\"description\":\"누구에게나 그런 날\\nsuri1987@naver.com\",\"createTime\":\"Sep 29, 2015 3:19:23 PM\",\"status\":\"verify\",\"articleCount\":65,\"socialUser\":false,\"writerCount\":113,\"followerCount\":6903},{\"userId\":\"o91\",\"userName\":\"노일영\",\"userImage\":\"http://t1.daumcdn.net/brunch/service/user/o91/image/VvENJOeolXn5TM0GjapMDElH2Sc\",\"profileId\":\"102\",\"description\":\"공간 칼럼니스트 노일영입니다. \\n하루 대부분을 앉아서 화내거나 돈을 쓰고\\n시간이 나면 걷거나 꿈꾸거나 글을 씁니다.\",\"createTime\":\"Sep 3, 2015 2:55:44 PM\",\"status\":\"verify\",\"articleCount\":15,\"socialUser\":false,\"writerCount\":29,\"followerCount\":89},{\"userId\":\"13Tu\",\"userName\":\"greenut\",\"userImage\":\"http://t1.daumcdn.net/brunch/service/user/13Tu/image/pOZ67xL616135ZEq0dwuMI-SdOE.jpg\",\"profileId\":\"greenut90\",\"description\":\"green+peanut\\u003dgreenut, 초록땅콩. 느린 시간을 사랑하는 일러스트레이터 greenut 김혜련입니다. / Contact - greenut90@naver.com\",\"createTime\":\"Jan 9, 2016 9:03:31 PM\",\"status\":\"verify\",\"articleCount\":74,\"socialUser\":false,\"writerCount\":34,\"followerCount\":1332}],\"title\":\"\\u003cb\\u003e감성 에세이\\u003c/b\\u003e 작가\",\"keyword\":\"15\"}","contents":{"profileList":[{"userId":"kEJ","userName":"공인식","userImage":"http://t1.daumcdn.net/brunch/service/user/kEJ/image/FX9j4b1ID4QSWILcJMOGct1OAcQ.jpeg","profileId":"alwayswithya","profileImage":null,"description":"Everything is a test.","createTime":1440555430000,"status":"verify","articleCount":53,"socialUser":false,"writerCount":52,"followerCount":55,"restrictTime":null},{"userId":"tlV","userName":"언이","userImage":"http://t1.daumcdn.net/brunch/service/user/tlV/image/6KmptzJ7-Bh_CkRVFl3z3epoooM","profileId":"zkwmfk","profileImage":null,"description":"언이의 브런치 입니다","createTime":1442407645000,"status":"verify","articleCount":103,"socialUser":false,"writerCount":108,"followerCount":109,"restrictTime":null},{"userId":"suk","userName":"badac","userImage":"http://t1.daumcdn.net/brunch/service/guest/image/A4-6Hd9XNmSlYX--kcYGByFo7Y0.png","profileId":"slowbadac","profileImage":null,"description":"새내기 귀촌인.\n자급지향 시골독립 생활인.","createTime":1442230303000,"status":"verify","articleCount":35,"socialUser":false,"writerCount":5,"followerCount":1434,"restrictTime":null},{"userId":"mGD","userName":"summer","userImage":"http://t1.daumcdn.net/brunch/service/user/mGD/image/xTYjZiT3alH0dN1VQWrwXHXPdhY","profileId":"summ-er","profileImage":null,"description":"너무도 소중한 일상의 평화","createTime":1440981837000,"status":"verify","articleCount":55,"socialUser":false,"writerCount":14,"followerCount":170,"restrictTime":null},{"userId":"t48","userName":"황길환","userImage":"http://t1.daumcdn.net/brunch/service/user/t48/image/pCs76b8nrNZ2Q67wXk8Kh6os0ew.png","profileId":"brunchxjk0","profileImage":null,"description":"언론정보학과에서 Human-Computer Interaction을 공부하는 대학원생입니다. 인공지능과 대화에 관심이 많습니다. :)","createTime":1442368607000,"status":"verify","articleCount":22,"socialUser":false,"writerCount":40,"followerCount":281,"restrictTime":null},{"userId":"loV","userName":"graysbook","userImage":"http://t1.daumcdn.net/brunch/service/guest/image/mN1-vvbrW3e4UHuPfERKoJJbFxY.png","profileId":"graysbook","profileImage":null,"description":"마들렌","createTime":1440693569000,"status":"verify","articleCount":25,"socialUser":false,"writerCount":24,"followerCount":219,"restrictTime":null},{"userId":"b15","userName":"윤군","userImage":"http://t1.daumcdn.net/brunch/service/user/b15/image/lfiSOkoEtGyPEUeJ31IvjHxL9S4","profileId":"yunjihoon","profileImage":null,"description":"타로카드를 읽고\n사랑 앞에서 이별을 씁니다","createTime":1437695759000,"status":"verify","articleCount":247,"socialUser":false,"writerCount":165,"followerCount":1999,"restrictTime":null},{"userId":"QHD","userName":"새벽 세시","userImage":"http://t1.daumcdn.net/brunch/service/guest/image/rjhQS7dxEdA7PphKnNJsfRBL0QE.png","profileId":"jay8zg0","profileImage":null,"description":"당신의 새벽 세시.\n\nwww.facebook.com/yours3am","createTime":1448394605000,"status":"verify","articleCount":200,"socialUser":false,"writerCount":0,"followerCount":5189,"restrictTime":null},{"userId":"6Hi","userName":"Hong Sukwoo","userImage":"http://t1.daumcdn.net/brunch/service/guest/image/j0IlNUt1rl1wmXuD8Mh7ljlb1wU","profileId":"yourboyhood","profileImage":null,"description":"Fashion journalist and essayist.\n<The NAVY Magazine> 에디터, @TheNAVYLab 디렉터.","createTime":1436082368000,"status":"verify","articleCount":138,"socialUser":false,"writerCount":0,"followerCount":1179,"restrictTime":null},{"userId":"23F6","userName":"씨앤우즈","userImage":"http://t1.daumcdn.net/brunch/service/guest/image/Ev3jt2LEVbrUxkGG-hYcaOjhcIk.png","profileId":"heat0508","profileImage":null,"description":"어느날 꿈에서 깨었다. 물에서 나온 사람처럼 발아래 꿈의 잔해들이 뚝뚝 떨어졌다. 그렇게 바닥에 그려진 무늬들을 글로 옮기기 시작했다.","createTime":1465731954000,"status":"verify","articleCount":56,"socialUser":false,"writerCount":1,"followerCount":1208,"restrictTime":null},{"userId":"Qcl","userName":"아흔아홉","userImage":"http://t1.daumcdn.net/brunch/service/user/Qcl/image/wFRK7xzrzVfzKY5MNzVihZt9Ph0.jpg","profileId":"hola99","profileImage":null,"description":"그림쟁이","createTime":1448214292000,"status":"verify","articleCount":17,"socialUser":false,"writerCount":3,"followerCount":923,"restrictTime":null},{"userId":"1WRs","userName":"민트코끼리","userImage":"http://t1.daumcdn.net/brunch/service/user/1WRs/image/GeVN9IMoonsQbxYUOUgaTgIXRMI.jpeg","profileId":"mintelephant","profileImage":null,"description":"말 못했던 시절의 기억, 일상의 기록 ,\n 필름 편지를 쓰는 치과의사","createTime":1463043917000,"status":"verify","articleCount":54,"socialUser":false,"writerCount":14,"followerCount":170,"restrictTime":null},{"userId":"2kMn","userName":"Lion Kid","userImage":"http://t1.daumcdn.net/brunch/service/user/2kMn/image/h-y6YVXTSgPpq6HUdlj8ZM_8X4Q.png","profileId":"basenell","profileImage":null,"description":"잡다하지만, 방대하지는 못한 관심사.\nintherainglow@gmail.com","createTime":1472034569000,"status":"verify","articleCount":160,"socialUser":false,"writerCount":1,"followerCount":1461,"restrictTime":null},{"userId":"1lRv","userName":"네오소울","userImage":"http://t1.daumcdn.net/brunch/service/user/1lRv/image/Ibs5ZfV0jvnhdoW8hfEKwluxX-I.jpg","profileId":"artnsoul","profileImage":null,"description":"진정한 의미의 관람객으로서의 글쓰기\n듣고 보고 읽기를 통해 그려보는 마음의 파동.","createTime":1458277942000,"status":"verify","articleCount":30,"socialUser":false,"writerCount":38,"followerCount":291,"restrictTime":null},{"userId":"260l","userName":"cirin","userImage":"http://t1.daumcdn.net/brunch/service/user/260l/image/Rb5yIUwbzz8F_fVlivzluRs4pxc.png","profileId":"cirin","profileImage":null,"description":"어떤 문장들은 그림처럼 남는다.","createTime":1466754812000,"status":"verify","articleCount":125,"socialUser":false,"writerCount":1,"followerCount":1545,"restrictTime":null},{"userId":"3w4D","userName":"김수현","userImage":"http://t1.daumcdn.net/brunch/service/guest/image/Y6S4GfVUWhYFaHDHk2Isb9CCSls","profileId":"ipretty0217","profileImage":null,"description":"<나는 나로 살기로 했다> 작가 김수현입니다.","createTime":1494222255000,"status":"verify","articleCount":5,"socialUser":false,"writerCount":1,"followerCount":1080,"restrictTime":null},{"userId":"7vx","userName":"Ossian","userImage":"http://t1.daumcdn.net/brunch/service/user/7vx/image/5F03vl2q6HS4wvNzCFvNYNyXNcA","profileId":"ossian","profileImage":null,"description":"꿈을 꾸며 글을 쓰고, \n글을 쓰며 꿈을 꿉니다.","createTime":1436332589000,"status":"verify","articleCount":104,"socialUser":false,"writerCount":96,"followerCount":2816,"restrictTime":null},{"userId":"3aCS","userName":"장연정","userImage":"http://t1.daumcdn.net/brunch/service/user/3aCS/image/W8-mBXX5wzIh7l1N3WS-stpdPf8.jpg","profileId":"jazzstream","profileImage":null,"description":"긴 글, 때때로 짧은 노랫말을 씁니다.","createTime":1488460849000,"status":"verify","articleCount":9,"socialUser":false,"writerCount":1,"followerCount":99,"restrictTime":null},{"userId":"3kpG","userName":"김수민","userImage":"http://t1.daumcdn.net/brunch/service/guest/image/c5Cfx6BZt9cMCbRNoVEb1altvck","profileId":"writersumin","profileImage":null,"description":"한 사람을 잃고 한 페이지를 채워가는 작가 김수민입니다. 어떤 말로도 위로가 안 되는 당신이 부디 위로가 되기를.","createTime":1490949726000,"status":"verify","articleCount":5,"socialUser":false,"writerCount":1,"followerCount":501,"restrictTime":null},{"userId":"r5H","userName":"홍환","userImage":"http://t1.daumcdn.net/brunch/service/guest/image/WCOgIfFR6GHDtgyk10wkgKEfDyU","profileId":"kyangkyang","profileImage":null,"description":"일상관찰자","createTime":1441873993000,"status":"verify","articleCount":131,"socialUser":false,"writerCount":63,"followerCount":259,"restrictTime":null},{"userId":"1gtW","userName":"Jua","userImage":"http://t1.daumcdn.net/brunch/service/user/1gtW/image/DLxzyna28uR62_1OF49rjmxqw2U.jpg","profileId":"juabae","profileImage":null,"description":"나를 찾고 동시에 버리는 여행을 한다. 거리에서 사람과 삶의 아름다움을 발견하고 찍는다. 마음이 담긴 글을 통해 누군가에게 위로가 되길 소망한다.\ninstagram@jua_bae","createTime":1456574301000,"status":"verify","articleCount":33,"socialUser":false,"writerCount":20,"followerCount":1481,"restrictTime":null},{"userId":"91x","userName":"Yoona Kim","userImage":"http://t1.daumcdn.net/brunch/service/user/91x/image/XTP01aK6gXYtQh_8vf_NkCeXQWQ.jpg","profileId":"intlovesong","profileImage":null,"description":"작가 #색에미친청춘\nynkimj@gmail.com","createTime":1436930323000,"status":"verify","articleCount":52,"socialUser":false,"writerCount":32,"followerCount":1695,"restrictTime":null},{"userId":"1ar6","userName":"김덕영","userImage":"http://t1.daumcdn.net/brunch/service/guest/image/HvbOUDaQX9HoqtENXioFagIxGSw.jpg","profileId":"altna84","profileImage":null,"description":"다큐멘터리를 제작하다 이제는 글쓰는 작가로 변신 중입니다. 서촌의 작은 골목길 까페, '김PD의 통의동 스토리'에서 조금은 색다른 방식으로 창작을 하면서 사람들과 만나고 있습니다.","createTime":1454579019000,"status":"verify","articleCount":89,"socialUser":false,"writerCount":10,"followerCount":4209,"restrictTime":null},{"userId":"szK","userName":"살찐 병아리","userImage":"http://t1.daumcdn.net/brunch/service/user/szK/image/vVKMaXFbfX72TGheLucfaxb4zHw.jpg","profileId":"keh7890","profileImage":null,"description":"공감되는 토탁토닥 이야기","createTime":1442248667000,"status":"verify","articleCount":85,"socialUser":false,"writerCount":7,"followerCount":2205,"restrictTime":null},{"userId":"oK4","userName":"장작가","userImage":"http://t1.daumcdn.net/brunch/service/user/oK4/image/tUFfMYI4xQng8qABQvOWAu6inwM.JPG","profileId":"yogurtradio","profileImage":null,"description":"전 다큐멘터리 방송작가\n사랑, 증오, 상처, 위로 등.\n우리가 사는 세상을 담담하게 이야기하는 곳. [이메일] yogurtradio@naver.com","createTime":1441372088000,"status":"verify","articleCount":78,"socialUser":false,"writerCount":7,"followerCount":1238,"restrictTime":null},{"userId":"7KD","userName":"남시언","userImage":"http://t1.daumcdn.net/brunch/service/user/7KD/image/Ye1GoUvRynIvoWoDQa7xRbQO5EU.JPG","profileId":"namsieon","profileImage":null,"description":"창조적 꼴통, 작가,  <1인분 청춘> <인생을 바꾸는 기적의 블로그> <아름다운 사표>의 저자, 취미는 멍 때리기, me@namsieon.com","createTime":1436410743000,"status":"verify","articleCount":87,"socialUser":false,"writerCount":5,"followerCount":1797,"restrictTime":null},{"userId":"11PJ","userName":"김도경","userImage":"http://t1.daumcdn.net/brunch/service/user/11PJ/image/Z_TjTxN11hsle5POp1a-WmkjBs0.jpg","profileId":"this7day","profileImage":null,"description":"그림에세이,웹툰,캐리커쳐,캘리그라피를 만드는 김도경의 브런치입니다.\ndreampen@naver.com","createTime":1451750432000,"status":"verify","articleCount":41,"socialUser":false,"writerCount":8,"followerCount":2146,"restrictTime":null},{"userId":"yfq","userName":"그럼에도 불구하고","userImage":"http://t1.daumcdn.net/brunch/service/user/yfq/image/TxUHSYmzLdBuPKhGsLQcPF3ZuVE","profileId":"shoostory","profileImage":null,"description":"누구에게나 그런 날\nsuri1987@naver.com","createTime":1443507563000,"status":"verify","articleCount":65,"socialUser":false,"writerCount":113,"followerCount":6903,"restrictTime":null},{"userId":"o91","userName":"노일영","userImage":"http://t1.daumcdn.net/brunch/service/user/o91/image/VvENJOeolXn5TM0GjapMDElH2Sc","profileId":"102","profileImage":null,"description":"공간 칼럼니스트 노일영입니다. \n하루 대부분을 앉아서 화내거나 돈을 쓰고\n시간이 나면 걷거나 꿈꾸거나 글을 씁니다.","createTime":1441259744000,"status":"verify","articleCount":15,"socialUser":false,"writerCount":29,"followerCount":89,"restrictTime":null},{"userId":"13Tu","userName":"greenut","userImage":"http://t1.daumcdn.net/brunch/service/user/13Tu/image/pOZ67xL616135ZEq0dwuMI-SdOE.jpg","profileId":"greenut90","profileImage":null,"description":"green+peanut=greenut, 초록땅콩. 느린 시간을 사랑하는 일러스트레이터 greenut 김혜련입니다. / Contact - greenut90@naver.com","createTime":1452341011000,"status":"verify","articleCount":74,"socialUser":false,"writerCount":34,"followerCount":1332,"restrictTime":null}],"title":"<b>감성 에세이</b> 작가","keyword":"15"},"createTime":null,"seq":7,"setNo":0},{"no":3521,"type":"KEYWORD_ARTICLE_AUTO","active":false,"deploy":false,"data":"{\"htmlKeywordTitle\":\"\\u003cb\\u003e미술\\u003c/b\\u003e·\\u003cb\\u003e예술\\u003c/b\\u003e\",\"keywordTitle\":\"미술·예술\",\"groupNo\":62,\"groupType\":\"group\",\"list\":[]}","contents":{"keyword":null,"htmlKeywordTitle":"<b>미술</b>·<b>예술</b>","keywordTitle":"미술·예술","moreLink":null,"groupNo":62,"groupType":"group","list":[]},"createTime":null,"seq":8,"setNo":0},{"no":3522,"type":"KEYWORD_USER","active":false,"deploy":false,"data":"{\"profileList\":[{\"userId\":\"2Z0\",\"userName\":\"김태연\",\"userImage\":\"http://t1.daumcdn.net/brunch/service/guest/image/hSZROiwajaE5_vnrMWO-_m8I6Qw\",\"profileId\":\"2691999\",\"description\":\"그림과 글과 사진은 예술, 자신에 대한 표현, 그 이상입니다\\n2691999@hanmail.net\",\"createTime\":\"Jun 17, 2015 10:33:30 PM\",\"status\":\"verify\",\"articleCount\":157,\"socialUser\":false,\"writerCount\":144,\"followerCount\":268},{\"userId\":\"3yEW\",\"userName\":\"트리플\",\"userImage\":\"http://t1.daumcdn.net/brunch/service/user/3yEW/image/osbCwHpEOlaPGyL7VJeB2OLvHvc.png\",\"profileId\":\"triple\",\"description\":\"해외여행 무료 가이드, 트리플!\\n깔끔한 어플로 만나보세요\\nhttps://triple.guide/\",\"createTime\":\"May 16, 2017 9:22:20 AM\",\"status\":\"verify\",\"articleCount\":11,\"socialUser\":false,\"writerCount\":2,\"followerCount\":120},{\"userId\":\"DLb\",\"userName\":\"정란수\",\"userImage\":\"http://t1.daumcdn.net/brunch/service/user/DLb/image/NAjaB6MCgKf20Hz0RzUXGALXVlI\",\"profileId\":\"tourism\",\"description\":\"여행다니면서 일하는 \\\"한량\\\"! \\n\\u003c여행을 가다, 희망을 보다\\u003e 저자이면서, 관광개발 컨설팅을 하고 돌아다님\\n www.facebook.com/projectsoo\",\"createTime\":\"Oct 10, 2015 3:13:03 PM\",\"status\":\"verify\",\"articleCount\":91,\"socialUser\":false,\"writerCount\":46,\"followerCount\":731},{\"userId\":\"zJ1\",\"userName\":\"JEE\",\"userImage\":\"http://t1.daumcdn.net/brunch/service/user/zJ1/image/qaBDm3B4cJRTen0Ud8zRudZnTMc.jpeg\",\"profileId\":\"optissi89\",\"description\":\"여행하는 카피라이터 \\n사진찍는 카피라이터\",\"createTime\":\"Oct 1, 2015 3:56:58 PM\",\"status\":\"verify\",\"articleCount\":16,\"socialUser\":false,\"writerCount\":41,\"followerCount\":806},{\"userId\":\"rsA\",\"userName\":\"써니디디\",\"userImage\":\"http://t1.daumcdn.net/brunch/service/guest/image/2_txvCDNDNE7F6tJ7tG6CCQlvrQ.png\",\"profileId\":\"sunnyluvin\",\"description\":\"Loved and Loving\",\"createTime\":\"Sep 11, 2015 7:28:41 PM\",\"status\":\"verify\",\"articleCount\":81,\"socialUser\":false,\"writerCount\":15,\"followerCount\":2228},{\"userId\":\"bqn\",\"userName\":\"초이스\",\"userImage\":\"http://t1.daumcdn.net/brunch/service/user/bqn/image/KvGRqEmNHuwwlRmp3oa_NK1OwKU.jpg\",\"profileId\":\"ochoic\",\"description\":\"기록한다는 것은 끝임없이 침식해 들어오는\\n인생의 무의미에 맞서는 일이기도 해\",\"createTime\":\"Jul 26, 2015 11:13:02 PM\",\"status\":\"verify\",\"articleCount\":21,\"socialUser\":false,\"writerCount\":20,\"followerCount\":745},{\"userId\":\"7SM\",\"userName\":\"누들\",\"userImage\":\"http://t1.daumcdn.net/brunch/service/user/7SM/image/7FEgoLDu6-jV3MRz81ZBQo-6LO4.png\",\"profileId\":\"breezynodul\",\"description\":\"업으로 글을 쓰고, 취미로 사진을 찍습니다.\\n행간읽기 발행인, BENEFIT 에디터\",\"createTime\":\"Jul 9, 2015 11:16:32 PM\",\"status\":\"verify\",\"articleCount\":28,\"socialUser\":false,\"writerCount\":8,\"followerCount\":1268},{\"userId\":\"1gtW\",\"userName\":\"Jua\",\"userImage\":\"http://t1.daumcdn.net/brunch/service/user/1gtW/image/DLxzyna28uR62_1OF49rjmxqw2U.jpg\",\"profileId\":\"juabae\",\"description\":\"나를 찾고 동시에 버리는 여행을 한다. 거리에서 사람과 삶의 아름다움을 발견하고 찍는다. 마음이 담긴 글을 통해 누군가에게 위로가 되길 소망한다.\\ninstagram@jua_bae\",\"createTime\":\"Feb 27, 2016 8:58:21 PM\",\"status\":\"verify\",\"articleCount\":33,\"socialUser\":false,\"writerCount\":20,\"followerCount\":1481},{\"userId\":\"r0j\",\"userName\":\"안태현\",\"userImage\":\"http://t1.daumcdn.net/brunch/service/guest/image/PJA6ZhwaJ7i-QtgozbBTGvY0QAI\",\"profileId\":\"glad123\",\"description\":\"시를 쓰고 있는 안태현의 브런치입니다.\",\"createTime\":\"Sep 10, 2015 1:32:45 PM\",\"status\":\"verify\",\"articleCount\":25,\"socialUser\":false,\"writerCount\":5,\"followerCount\":125},{\"userId\":\"BTh\",\"userName\":\"rae\",\"userImage\":\"http://t1.daumcdn.net/brunch/service/guest/image/uCFDtT4Wa9bjcZ3RaxONLbsgDeg.png\",\"profileId\":\"raekim\",\"description\":\"가끔 여행을 떠나 사진과 글을 남깁니다.\",\"createTime\":\"Oct 5, 2015 3:37:02 PM\",\"status\":\"verify\",\"articleCount\":45,\"socialUser\":false,\"writerCount\":164,\"followerCount\":10672},{\"userId\":\"5uz\",\"userName\":\"이삼일 프로젝트\",\"userImage\":\"http://t1.daumcdn.net/brunch/service/user/5uz/image/HzhUsNnSRp-Bn-PWkC8MUQgfvAM\",\"profileId\":\"231project\",\"description\":\"여행의 시간과 공간, 사람의 이야기\",\"createTime\":\"Jul 1, 2015 9:32:37 PM\",\"status\":\"verify\",\"articleCount\":56,\"socialUser\":false,\"writerCount\":40,\"followerCount\":302},{\"userId\":\"2uf\",\"userName\":\"리모\",\"userImage\":\"http://t1.daumcdn.net/brunch/service/user/2uf/image/V1fLKdr03r7a1Xi7A_JE5R4GVzU.jpg\",\"profileId\":\"zazzseo\",\"description\":\"-시간을 멈추는 드로잉-과\\n-드로잉 제주-의 저자,\\n드로잉으로 남긴 여행과 일상의\\n솔직한 기록들\\nzazzseo@naver.com\",\"createTime\":\"May 18, 2015 4:02:35 PM\",\"status\":\"verify\",\"articleCount\":45,\"socialUser\":false,\"writerCount\":59,\"followerCount\":8216},{\"userId\":\"2Uj\",\"userName\":\"돈 없는 부부의 우아한 서울살이 by 한 달에 한 도시\",\"userImage\":\"http://t1.daumcdn.net/brunch/service/user/2Uj/image/h4xrFbzgeGcvouZ2rdmcVpwhd74.jpg\",\"profileId\":\"seoulsale\",\"description\":\"글로 담을 만한 인생이 되려고 부단히 노력 중 입니다.\",\"createTime\":\"Jun 14, 2015 8:13:05 PM\",\"status\":\"verify\",\"articleCount\":120,\"socialUser\":false,\"writerCount\":2785,\"followerCount\":7182},{\"userId\":\"1VRQ\",\"userName\":\"Jenny\",\"userImage\":\"http://t1.daumcdn.net/brunch/service/user/1VRQ/image/g1f_p38_BIMNwwfgmukTTs8q9ck.jpg\",\"profileId\":\"lanatravel\",\"description\":\"원하면 이루어진다\",\"createTime\":\"May 9, 2016 12:23:52 AM\",\"status\":\"verify\",\"articleCount\":33,\"socialUser\":false,\"writerCount\":41,\"followerCount\":240},{\"userId\":\"79q\",\"userName\":\"yoonash\",\"userImage\":\"http://t1.daumcdn.net/brunch/service/user/79q/image/mb2WJQ7rA6vBoFLBpZp0EETVgjs\",\"profileId\":\"yoonash\",\"description\":\"아날로그한 취향을 가진 마케터\\nInstagram @alohayoon\",\"createTime\":\"Jul 7, 2015 12:45:46 AM\",\"status\":\"verify\",\"articleCount\":57,\"socialUser\":false,\"writerCount\":80,\"followerCount\":5970},{\"userId\":\"CVl\",\"userName\":\"곰지\",\"userImage\":\"http://t1.daumcdn.net/brunch/service/user/CVl/image/oEYpna9SdTufrfRdKFCXSjS2Xjo.JPG\",\"profileId\":\"realgomji\",\"description\":\"너에게 읽히는 한 권의 책이고 싶다.\\n사진을 찍고 생각을 끄적입니다.\\n당신을 위로할 마음속 대사\",\"createTime\":\"Oct 8, 2015 12:55:26 AM\",\"status\":\"verify\",\"articleCount\":8,\"socialUser\":false,\"writerCount\":46,\"followerCount\":877},{\"userId\":\"STq\",\"userName\":\"ExpediaKR\",\"userImage\":\"http://t1.daumcdn.net/brunch/service/user/STq/image/N5wxRTMZMWEG6eVLXnJ6hPDYwzo.jpg\",\"profileId\":\"expediakr\",\"description\":\"당신이 원하는 전 세계의 다양한 여행 정보 #익스피디아의발견\\n익스피디아 모바일앱 8% 할인코드 (EXAPP2017MAY)\\n자세히보기 ▶ http://bit.ly/1QI0Zku\",\"createTime\":\"Dec 3, 2015 9:05:00 PM\",\"status\":\"verify\",\"articleCount\":166,\"socialUser\":false,\"writerCount\":3,\"followerCount\":6041},{\"userId\":\"8Ox\",\"userName\":\"석류\",\"userImage\":\"http://t1.daumcdn.net/brunch/service/guest/image/rfeWALXSE4GZcb8wY33IQqbR4LA.png\",\"profileId\":\"fantasma\",\"description\":\"책 \\u003c찬란하고도 쓸쓸한 너라는 계절\\u003e을 썼습니다. 삶을 여행하며 여러 모습들을 이야기합니다.\",\"createTime\":\"Jul 14, 2015 4:27:28 PM\",\"status\":\"verify\",\"articleCount\":263,\"socialUser\":false,\"writerCount\":1,\"followerCount\":213},{\"userId\":\"2hry\",\"userName\":\"시에\",\"userImage\":\"http://t1.daumcdn.net/brunch/service/user/2hry/image/sf0GFGYPDfaDSFtHc974mIpUcDI.png\",\"profileId\":\"miheexiepark\",\"description\":\"아직은 어중간한 인간\\nmtsaram@naver.com\",\"createTime\":\"Aug 10, 2016 6:46:37 PM\",\"status\":\"verify\",\"articleCount\":33,\"socialUser\":false,\"writerCount\":3,\"followerCount\":469},{\"userId\":\"2lED\",\"userName\":\"muum\",\"userImage\":\"http://t1.daumcdn.net/brunch/service/user/2lED/image/RtDi-fxyuPwniFS2AsTbpEEufCw.jpg\",\"profileId\":\"muum\",\"description\":\"시간이 흘러가는 것이 아니라, 내가 흘러가는 것.\\n여행은 떠나가는 것이 아니라, 내게 다가가는 것.\",\"createTime\":\"Aug 28, 2016 10:52:49 PM\",\"status\":\"verify\",\"articleCount\":97,\"socialUser\":false,\"writerCount\":45,\"followerCount\":115},{\"userId\":\"JkV\",\"userName\":\"하늘바라기\",\"userImage\":\"http://t1.daumcdn.net/brunch/service/user/JkV/image/9W8KePvWZ6mE3iSvXtvnCvweuEE\",\"profileId\":\"skysay75\",\"description\":\"여행으로 꿈을 그리는 낭만주의자.  따뜻한 시선으로 세상을 바라보고 싶은 30대 소녀.\",\"createTime\":\"Oct 29, 2015 1:21:05 AM\",\"status\":\"verify\",\"articleCount\":20,\"socialUser\":false,\"writerCount\":65,\"followerCount\":3120},{\"userId\":\"2jhw\",\"userName\":\"이훈호\",\"userImage\":\"http://t1.daumcdn.net/brunch/service/user/2jhw/image/IZpBm4MdkVrcq6Oee6oSWu8hvnQ.jpg\",\"profileId\":\"stranger88\",\"description\":\"가끔 떠나고 자주 방황합니다. \\n여행의 순간을 수집합니다.\\nhunophoto@gmail.com\",\"createTime\":\"Aug 18, 2016 10:08:02 AM\",\"status\":\"verify\",\"articleCount\":24,\"socialUser\":false,\"writerCount\":50,\"followerCount\":671},{\"userId\":\"1VcB\",\"userName\":\"생활여행자\",\"userImage\":\"http://t1.daumcdn.net/brunch/service/user/1VcB/image/BSetZXt5aGbiXPm8fhf9i3C2otc.jpg\",\"profileId\":\"yejinchoi\",\"description\":\"별 볼 일 없는 생활여행자의 로그\",\"createTime\":\"May 6, 2016 5:39:54 AM\",\"status\":\"verify\",\"articleCount\":25,\"socialUser\":false,\"writerCount\":7,\"followerCount\":1314},{\"userId\":\"UWP\",\"userName\":\"미나미\",\"userImage\":\"http://t1.daumcdn.net/brunch/service/user/UWP/image/b3baYlihgVNDsq0Z1zruN7pWQ3I.JPG\",\"profileId\":\"minhaaami\",\"description\":\"떠남과 머무름 사이\\ninsta @minami.foto\",\"createTime\":\"Dec 11, 2015 4:44:08 PM\",\"status\":\"verify\",\"articleCount\":20,\"socialUser\":false,\"writerCount\":31,\"followerCount\":791},{\"userId\":\"2ZsU\",\"userName\":\"몽땅몰타\",\"userImage\":\"http://t1.daumcdn.net/brunch/service/user/2ZsU/image/-9eHuYtNIcq23nQi8nBvfreFBro.jpg\",\"profileId\":\"montempsmalta\",\"description\":\"몰타에서의 시간 그리고 몰타의 모든 것을 공유합니다.\\nby 임 Ines, 장 Jane\",\"createTime\":\"Jan 31, 2017 1:21:02 PM\",\"status\":\"verify\",\"articleCount\":45,\"socialUser\":false,\"writerCount\":15,\"followerCount\":280},{\"userId\":\"BMf\",\"userName\":\"장준우\",\"userImage\":\"http://t1.daumcdn.net/brunch/service/user/BMf/image/pafMc2DM_UHN1wOOq0gLg5v6mGo.jpg\",\"profileId\":\"julieted17\",\"description\":\"요리하고 사진찍고 글을 씁니다 그리고\",\"createTime\":\"Oct 5, 2015 10:15:06 AM\",\"status\":\"verify\",\"articleCount\":32,\"socialUser\":false,\"writerCount\":36,\"followerCount\":2564},{\"userId\":\"4am\",\"userName\":\"노건\",\"userImage\":\"http://t1.daumcdn.net/brunch/service/user/4am/image/o1Kaesrg6NQv3hiYlMPX_Cn7tD8\",\"profileId\":\"trip\",\"description\":\"여행이 유일한 일탈, 흔한 30대 직장인\",\"createTime\":\"Jun 26, 2015 5:17:37 PM\",\"status\":\"verify\",\"articleCount\":20,\"socialUser\":false,\"writerCount\":52,\"followerCount\":4266},{\"userId\":\"sTw\",\"userName\":\"그루\",\"userImage\":\"http://t1.daumcdn.net/brunch/service/guest/image/Vic9Jhu5uanR-jTl4b8e3901z8M\",\"profileId\":\"madder\",\"description\":\"길에게 길을 묻다\",\"createTime\":\"Sep 15, 2015 10:43:52 PM\",\"status\":\"verify\",\"articleCount\":165,\"socialUser\":false,\"writerCount\":20,\"followerCount\":932},{\"userId\":\"Wo9\",\"userName\":\"Sentimental Vagabond\",\"userImage\":\"http://t1.daumcdn.net/brunch/service/user/Wo9/image/xfOlcDM1t7v6BEjJiipHaOwvhu4.jpg\",\"profileId\":\"peony\",\"description\":\"보고 듣고 느끼고. 먹고 마시고 즐기고. 살며 사랑하며 배우며.\",\"createTime\":\"Dec 14, 2015 8:45:54 AM\",\"status\":\"verify\",\"articleCount\":27,\"socialUser\":false,\"writerCount\":103,\"followerCount\":947},{\"userId\":\"1WHt\",\"userName\":\"에디터 조하나\",\"userImage\":\"http://t1.daumcdn.net/brunch/service/guest/image/sEHjgseevA-c4F2pKrO4w1QpJGM\",\"profileId\":\"editorh\",\"description\":\"잘 다니던 패션지 그만 두고 태국 외딴 섬 꼬따오에서 스쿠버 다이빙하는 PADI 강사이자 에디터, 조하나입니다.\",\"createTime\":\"May 12, 2016 2:14:29 AM\",\"status\":\"verify\",\"articleCount\":95,\"socialUser\":false,\"writerCount\":2,\"followerCount\":940}],\"title\":\"\\u003cb\\u003e여행\\u003c/b\\u003e 작가\",\"keyword\":\"1\"}","contents":{"profileList":[{"userId":"2Z0","userName":"김태연","userImage":"http://t1.daumcdn.net/brunch/service/guest/image/hSZROiwajaE5_vnrMWO-_m8I6Qw","profileId":"2691999","profileImage":null,"description":"그림과 글과 사진은 예술, 자신에 대한 표현, 그 이상입니다\n2691999@hanmail.net","createTime":1434548010000,"status":"verify","articleCount":157,"socialUser":false,"writerCount":144,"followerCount":268,"restrictTime":null},{"userId":"3yEW","userName":"트리플","userImage":"http://t1.daumcdn.net/brunch/service/user/3yEW/image/osbCwHpEOlaPGyL7VJeB2OLvHvc.png","profileId":"triple","profileImage":null,"description":"해외여행 무료 가이드, 트리플!\n깔끔한 어플로 만나보세요\nhttps://triple.guide/","createTime":1494894140000,"status":"verify","articleCount":11,"socialUser":false,"writerCount":2,"followerCount":120,"restrictTime":null},{"userId":"DLb","userName":"정란수","userImage":"http://t1.daumcdn.net/brunch/service/user/DLb/image/NAjaB6MCgKf20Hz0RzUXGALXVlI","profileId":"tourism","profileImage":null,"description":"여행다니면서 일하는 \"한량\"! \n<여행을 가다, 희망을 보다> 저자이면서, 관광개발 컨설팅을 하고 돌아다님\n www.facebook.com/projectsoo","createTime":1444457583000,"status":"verify","articleCount":91,"socialUser":false,"writerCount":46,"followerCount":731,"restrictTime":null},{"userId":"zJ1","userName":"JEE","userImage":"http://t1.daumcdn.net/brunch/service/user/zJ1/image/qaBDm3B4cJRTen0Ud8zRudZnTMc.jpeg","profileId":"optissi89","profileImage":null,"description":"여행하는 카피라이터 \n사진찍는 카피라이터","createTime":1443682618000,"status":"verify","articleCount":16,"socialUser":false,"writerCount":41,"followerCount":806,"restrictTime":null},{"userId":"rsA","userName":"써니디디","userImage":"http://t1.daumcdn.net/brunch/service/guest/image/2_txvCDNDNE7F6tJ7tG6CCQlvrQ.png","profileId":"sunnyluvin","profileImage":null,"description":"Loved and Loving","createTime":1441967321000,"status":"verify","articleCount":81,"socialUser":false,"writerCount":15,"followerCount":2228,"restrictTime":null},{"userId":"bqn","userName":"초이스","userImage":"http://t1.daumcdn.net/brunch/service/user/bqn/image/KvGRqEmNHuwwlRmp3oa_NK1OwKU.jpg","profileId":"ochoic","profileImage":null,"description":"기록한다는 것은 끝임없이 침식해 들어오는\n인생의 무의미에 맞서는 일이기도 해","createTime":1437919982000,"status":"verify","articleCount":21,"socialUser":false,"writerCount":20,"followerCount":745,"restrictTime":null},{"userId":"7SM","userName":"누들","userImage":"http://t1.daumcdn.net/brunch/service/user/7SM/image/7FEgoLDu6-jV3MRz81ZBQo-6LO4.png","profileId":"breezynodul","profileImage":null,"description":"업으로 글을 쓰고, 취미로 사진을 찍습니다.\n행간읽기 발행인, BENEFIT 에디터","createTime":1436451392000,"status":"verify","articleCount":28,"socialUser":false,"writerCount":8,"followerCount":1268,"restrictTime":null},{"userId":"1gtW","userName":"Jua","userImage":"http://t1.daumcdn.net/brunch/service/user/1gtW/image/DLxzyna28uR62_1OF49rjmxqw2U.jpg","profileId":"juabae","profileImage":null,"description":"나를 찾고 동시에 버리는 여행을 한다. 거리에서 사람과 삶의 아름다움을 발견하고 찍는다. 마음이 담긴 글을 통해 누군가에게 위로가 되길 소망한다.\ninstagram@jua_bae","createTime":1456574301000,"status":"verify","articleCount":33,"socialUser":false,"writerCount":20,"followerCount":1481,"restrictTime":null},{"userId":"r0j","userName":"안태현","userImage":"http://t1.daumcdn.net/brunch/service/guest/image/PJA6ZhwaJ7i-QtgozbBTGvY0QAI","profileId":"glad123","profileImage":null,"description":"시를 쓰고 있는 안태현의 브런치입니다.","createTime":1441859565000,"status":"verify","articleCount":25,"socialUser":false,"writerCount":5,"followerCount":125,"restrictTime":null},{"userId":"BTh","userName":"rae","userImage":"http://t1.daumcdn.net/brunch/service/guest/image/uCFDtT4Wa9bjcZ3RaxONLbsgDeg.png","profileId":"raekim","profileImage":null,"description":"가끔 여행을 떠나 사진과 글을 남깁니다.","createTime":1444027022000,"status":"verify","articleCount":45,"socialUser":false,"writerCount":164,"followerCount":10672,"restrictTime":null},{"userId":"5uz","userName":"이삼일 프로젝트","userImage":"http://t1.daumcdn.net/brunch/service/user/5uz/image/HzhUsNnSRp-Bn-PWkC8MUQgfvAM","profileId":"231project","profileImage":null,"description":"여행의 시간과 공간, 사람의 이야기","createTime":1435753957000,"status":"verify","articleCount":56,"socialUser":false,"writerCount":40,"followerCount":302,"restrictTime":null},{"userId":"2uf","userName":"리모","userImage":"http://t1.daumcdn.net/brunch/service/user/2uf/image/V1fLKdr03r7a1Xi7A_JE5R4GVzU.jpg","profileId":"zazzseo","profileImage":null,"description":"-시간을 멈추는 드로잉-과\n-드로잉 제주-의 저자,\n드로잉으로 남긴 여행과 일상의\n솔직한 기록들\nzazzseo@naver.com","createTime":1431932555000,"status":"verify","articleCount":45,"socialUser":false,"writerCount":59,"followerCount":8216,"restrictTime":null},{"userId":"2Uj","userName":"돈 없는 부부의 우아한 서울살이 by 한 달에 한 도시","userImage":"http://t1.daumcdn.net/brunch/service/user/2Uj/image/h4xrFbzgeGcvouZ2rdmcVpwhd74.jpg","profileId":"seoulsale","profileImage":null,"description":"글로 담을 만한 인생이 되려고 부단히 노력 중 입니다.","createTime":1434280385000,"status":"verify","articleCount":120,"socialUser":false,"writerCount":2785,"followerCount":7182,"restrictTime":null},{"userId":"1VRQ","userName":"Jenny","userImage":"http://t1.daumcdn.net/brunch/service/user/1VRQ/image/g1f_p38_BIMNwwfgmukTTs8q9ck.jpg","profileId":"lanatravel","profileImage":null,"description":"원하면 이루어진다","createTime":1462721032000,"status":"verify","articleCount":33,"socialUser":false,"writerCount":41,"followerCount":240,"restrictTime":null},{"userId":"79q","userName":"yoonash","userImage":"http://t1.daumcdn.net/brunch/service/user/79q/image/mb2WJQ7rA6vBoFLBpZp0EETVgjs","profileId":"yoonash","profileImage":null,"description":"아날로그한 취향을 가진 마케터\nInstagram @alohayoon","createTime":1436197546000,"status":"verify","articleCount":57,"socialUser":false,"writerCount":80,"followerCount":5970,"restrictTime":null},{"userId":"CVl","userName":"곰지","userImage":"http://t1.daumcdn.net/brunch/service/user/CVl/image/oEYpna9SdTufrfRdKFCXSjS2Xjo.JPG","profileId":"realgomji","profileImage":null,"description":"너에게 읽히는 한 권의 책이고 싶다.\n사진을 찍고 생각을 끄적입니다.\n당신을 위로할 마음속 대사","createTime":1444233326000,"status":"verify","articleCount":8,"socialUser":false,"writerCount":46,"followerCount":877,"restrictTime":null},{"userId":"STq","userName":"ExpediaKR","userImage":"http://t1.daumcdn.net/brunch/service/user/STq/image/N5wxRTMZMWEG6eVLXnJ6hPDYwzo.jpg","profileId":"expediakr","profileImage":null,"description":"당신이 원하는 전 세계의 다양한 여행 정보 #익스피디아의발견\n익스피디아 모바일앱 8% 할인코드 (EXAPP2017MAY)\n자세히보기 ▶ http://bit.ly/1QI0Zku","createTime":1449144300000,"status":"verify","articleCount":166,"socialUser":false,"writerCount":3,"followerCount":6041,"restrictTime":null},{"userId":"8Ox","userName":"석류","userImage":"http://t1.daumcdn.net/brunch/service/guest/image/rfeWALXSE4GZcb8wY33IQqbR4LA.png","profileId":"fantasma","profileImage":null,"description":"책 <찬란하고도 쓸쓸한 너라는 계절>을 썼습니다. 삶을 여행하며 여러 모습들을 이야기합니다.","createTime":1436858848000,"status":"verify","articleCount":263,"socialUser":false,"writerCount":1,"followerCount":213,"restrictTime":null},{"userId":"2hry","userName":"시에","userImage":"http://t1.daumcdn.net/brunch/service/user/2hry/image/sf0GFGYPDfaDSFtHc974mIpUcDI.png","profileId":"miheexiepark","profileImage":null,"description":"아직은 어중간한 인간\nmtsaram@naver.com","createTime":1470822397000,"status":"verify","articleCount":33,"socialUser":false,"writerCount":3,"followerCount":469,"restrictTime":null},{"userId":"2lED","userName":"muum","userImage":"http://t1.daumcdn.net/brunch/service/user/2lED/image/RtDi-fxyuPwniFS2AsTbpEEufCw.jpg","profileId":"muum","profileImage":null,"description":"시간이 흘러가는 것이 아니라, 내가 흘러가는 것.\n여행은 떠나가는 것이 아니라, 내게 다가가는 것.","createTime":1472392369000,"status":"verify","articleCount":97,"socialUser":false,"writerCount":45,"followerCount":115,"restrictTime":null},{"userId":"JkV","userName":"하늘바라기","userImage":"http://t1.daumcdn.net/brunch/service/user/JkV/image/9W8KePvWZ6mE3iSvXtvnCvweuEE","profileId":"skysay75","profileImage":null,"description":"여행으로 꿈을 그리는 낭만주의자.  따뜻한 시선으로 세상을 바라보고 싶은 30대 소녀.","createTime":1446049265000,"status":"verify","articleCount":20,"socialUser":false,"writerCount":65,"followerCount":3120,"restrictTime":null},{"userId":"2jhw","userName":"이훈호","userImage":"http://t1.daumcdn.net/brunch/service/user/2jhw/image/IZpBm4MdkVrcq6Oee6oSWu8hvnQ.jpg","profileId":"stranger88","profileImage":null,"description":"가끔 떠나고 자주 방황합니다. \n여행의 순간을 수집합니다.\nhunophoto@gmail.com","createTime":1471482482000,"status":"verify","articleCount":24,"socialUser":false,"writerCount":50,"followerCount":671,"restrictTime":null},{"userId":"1VcB","userName":"생활여행자","userImage":"http://t1.daumcdn.net/brunch/service/user/1VcB/image/BSetZXt5aGbiXPm8fhf9i3C2otc.jpg","profileId":"yejinchoi","profileImage":null,"description":"별 볼 일 없는 생활여행자의 로그","createTime":1462480794000,"status":"verify","articleCount":25,"socialUser":false,"writerCount":7,"followerCount":1314,"restrictTime":null},{"userId":"UWP","userName":"미나미","userImage":"http://t1.daumcdn.net/brunch/service/user/UWP/image/b3baYlihgVNDsq0Z1zruN7pWQ3I.JPG","profileId":"minhaaami","profileImage":null,"description":"떠남과 머무름 사이\ninsta @minami.foto","createTime":1449819848000,"status":"verify","articleCount":20,"socialUser":false,"writerCount":31,"followerCount":791,"restrictTime":null},{"userId":"2ZsU","userName":"몽땅몰타","userImage":"http://t1.daumcdn.net/brunch/service/user/2ZsU/image/-9eHuYtNIcq23nQi8nBvfreFBro.jpg","profileId":"montempsmalta","profileImage":null,"description":"몰타에서의 시간 그리고 몰타의 모든 것을 공유합니다.\nby 임 Ines, 장 Jane","createTime":1485836462000,"status":"verify","articleCount":45,"socialUser":false,"writerCount":15,"followerCount":280,"restrictTime":null},{"userId":"BMf","userName":"장준우","userImage":"http://t1.daumcdn.net/brunch/service/user/BMf/image/pafMc2DM_UHN1wOOq0gLg5v6mGo.jpg","profileId":"julieted17","profileImage":null,"description":"요리하고 사진찍고 글을 씁니다 그리고","createTime":1444007706000,"status":"verify","articleCount":32,"socialUser":false,"writerCount":36,"followerCount":2564,"restrictTime":null},{"userId":"4am","userName":"노건","userImage":"http://t1.daumcdn.net/brunch/service/user/4am/image/o1Kaesrg6NQv3hiYlMPX_Cn7tD8","profileId":"trip","profileImage":null,"description":"여행이 유일한 일탈, 흔한 30대 직장인","createTime":1435306657000,"status":"verify","articleCount":20,"socialUser":false,"writerCount":52,"followerCount":4266,"restrictTime":null},{"userId":"sTw","userName":"그루","userImage":"http://t1.daumcdn.net/brunch/service/guest/image/Vic9Jhu5uanR-jTl4b8e3901z8M","profileId":"madder","profileImage":null,"description":"길에게 길을 묻다","createTime":1442324632000,"status":"verify","articleCount":165,"socialUser":false,"writerCount":20,"followerCount":932,"restrictTime":null},{"userId":"Wo9","userName":"Sentimental Vagabond","userImage":"http://t1.daumcdn.net/brunch/service/user/Wo9/image/xfOlcDM1t7v6BEjJiipHaOwvhu4.jpg","profileId":"peony","profileImage":null,"description":"보고 듣고 느끼고. 먹고 마시고 즐기고. 살며 사랑하며 배우며.","createTime":1450050354000,"status":"verify","articleCount":27,"socialUser":false,"writerCount":103,"followerCount":947,"restrictTime":null},{"userId":"1WHt","userName":"에디터 조하나","userImage":"http://t1.daumcdn.net/brunch/service/guest/image/sEHjgseevA-c4F2pKrO4w1QpJGM","profileId":"editorh","profileImage":null,"description":"잘 다니던 패션지 그만 두고 태국 외딴 섬 꼬따오에서 스쿠버 다이빙하는 PADI 강사이자 에디터, 조하나입니다.","createTime":1462986869000,"status":"verify","articleCount":95,"socialUser":false,"writerCount":2,"followerCount":940,"restrictTime":null}],"title":"<b>여행</b> 작가","keyword":"1"},"createTime":null,"seq":9,"setNo":0},{"no":3523,"type":"KEYWORD_ARTICLE_AUTO","active":false,"deploy":false,"data":"{\"htmlKeywordTitle\":\"\\u003cb\\u003e다이어트\\u003c/b\\u003e 삼매경\",\"keywordTitle\":\"다이어트 삼매경\",\"groupNo\":49,\"groupType\":\"group\",\"list\":[]}","contents":{"keyword":null,"htmlKeywordTitle":"<b>다이어트</b> 삼매경","keywordTitle":"다이어트 삼매경","moreLink":null,"groupNo":49,"groupType":"group","list":[]},"createTime":null,"seq":10,"setNo":0},{"no":3524,"type":"KEYWORD_ARTICLE_AUTO","active":false,"deploy":false,"data":"{\"htmlKeywordTitle\":\"\\u003cb\\u003e그림\\u003c/b\\u003e·\\u003cb\\u003e웹툰\\u003c/b\\u003e\",\"keywordTitle\":\"그림·웹툰\",\"groupNo\":34,\"groupType\":\"group\",\"list\":[]}","contents":{"keyword":null,"htmlKeywordTitle":"<b>그림</b>·<b>웹툰</b>","keywordTitle":"그림·웹툰","moreLink":null,"groupNo":34,"groupType":"group","list":[]},"createTime":null,"seq":11,"setNo":0},{"no":3525,"type":"KEYWORD_ARTICLE_AUTO","active":false,"deploy":false,"data":"{\"htmlKeywordTitle\":\"내 마음에 쏙 드는 \\u003cb\\u003e인테리어\\u003c/b\\u003e\",\"keywordTitle\":\"내 마음에 쏙 드는 인테리어\",\"groupNo\":71,\"groupType\":\"group\",\"list\":[]}","contents":{"keyword":null,"htmlKeywordTitle":"내 마음에 쏙 드는 <b>인테리어</b>","keywordTitle":"내 마음에 쏙 드는 인테리어","moreLink":null,"groupNo":71,"groupType":"group","list":[]},"createTime":null,"seq":12,"setNo":0},{"no":3526,"type":"KEYWORD_USER","active":false,"deploy":false,"data":"{\"profileList\":[{\"userId\":\"1cee\",\"userName\":\"박찬학\",\"userImage\":\"http://t1.daumcdn.net/brunch/service/guest/image/D0txy0Kh-p10JA6qsBju5nDSeK0\",\"profileId\":\"tel1638\",\"description\":\"이우학교 역사교사\",\"createTime\":\"Feb 12, 2016 1:53:06 PM\",\"status\":\"verify\",\"articleCount\":88,\"socialUser\":false,\"writerCount\":12,\"followerCount\":1313},{\"userId\":\"2fEJ\",\"userName\":\"UX 컨설턴트 전민수\",\"userImage\":\"http://t1.daumcdn.net/brunch/service/user/2fEJ/image/W2jzfbkxN-PnaLqxgR2ydurJLjM.jpg\",\"profileId\":\"ebprux\",\"description\":\"UX 컨설팅 ·UX리서치 전문 이비피알유엑스(www.ebprux.co.kr) 대표 이사 / UX 컨설팅 및 강의 문의 시 010.4308.7532 문자 주세요\",\"createTime\":\"Aug 2, 2016 2:54:34 PM\",\"status\":\"verify\",\"articleCount\":235,\"socialUser\":false,\"writerCount\":9,\"followerCount\":5966},{\"userId\":\"32mB\",\"userName\":\"모종린의 골목길 경제학\",\"userImage\":\"http://t1.daumcdn.net/brunch/service/user/32mB/image/RTNQIStIvk9aAgmIMoL3NZ2uJ5E.jpg\",\"profileId\":\"riglobalization\",\"description\":\"\\u003c작은 도시 큰 기업\\u003e 저자\\n\\u003c라이프스타일 도시\\u003e 저자\\nwww.facebook.com/jongryn.mo\",\"createTime\":\"Feb 7, 2017 10:13:15 AM\",\"status\":\"verify\",\"articleCount\":21,\"socialUser\":false,\"writerCount\":16,\"followerCount\":1003},{\"userId\":\"kZ6\",\"userName\":\"천쌤\",\"userImage\":\"http://t1.daumcdn.net/brunch/service/guest/image/BNeh0ltLFJgBGT87umnfbcxxR_8.png\",\"profileId\":\"visionary\",\"description\":\"철부지선생님과 아이들 그리고 수학이야기\",\"createTime\":\"Aug 27, 2015 1:59:05 AM\",\"status\":\"verify\",\"articleCount\":10,\"socialUser\":false,\"writerCount\":16,\"followerCount\":38},{\"userId\":\"sJu\",\"userName\":\"수요일밴드 박대현입니다\",\"userImage\":\"http://t1.daumcdn.net/brunch/service/guest/image/LMbZOvmuDFJX8KZYyOxO7NsB9wU\",\"profileId\":\"sooband\",\"description\":\"뭐 하나 제대로 하는 건 없지만 안 하는 건 없습니다.\",\"createTime\":\"Sep 15, 2015 2:42:30 PM\",\"status\":\"verify\",\"articleCount\":252,\"socialUser\":false,\"writerCount\":89,\"followerCount\":1729},{\"userId\":\"38P\",\"userName\":\"나는일학년담임\",\"userImage\":\"http://t1.daumcdn.net/brunch/service/user/38P/image/XXw3Rndx1XLI3cyHse8w3cQ0pYc\",\"profileId\":\"songjh03\",\"description\":\"농촌의 작은 초등학교 1학년 교사입니다. 만 여섯 살 갓 넘은 아이들이 성장하느라 얼마나 애를 쓰는지, 그 노력들이 왜 숭고한지, 성장의 경건함을 보여드리고 싶습\",\"createTime\":\"Jun 22, 2015 10:13:13 AM\",\"status\":\"verify\",\"articleCount\":128,\"socialUser\":false,\"writerCount\":43,\"followerCount\":4007},{\"userId\":\"1eCc\",\"userName\":\"모순선생\",\"userImage\":\"http://t1.daumcdn.net/brunch/service/user/1eCc/image/JzrAA4uhSiWu670ygl9Q_Y4K9IE.png\",\"profileId\":\"hshello\",\"description\":\"교사는 되는 것이 아니라 되어지는 것이다, \\u0027티처메카 중등 임용 교육학 논술 강사\\u0027\",\"createTime\":\"Feb 20, 2016 9:59:31 AM\",\"status\":\"verify\",\"articleCount\":32,\"socialUser\":false,\"writerCount\":26,\"followerCount\":890},{\"userId\":\"zTK\",\"userName\":\"호호할멈\",\"userImage\":\"http://t1.daumcdn.net/brunch/service/guest/image/c1mqW8nXch7NWaaIzbqWGIEhanU.png\",\"profileId\":\"yooatic84\",\"description\":\"시덥잖은 잡생각을 끝까지 꺼내 \\n잡생각에 대한 생각을 정리합니다.\",\"createTime\":\"Oct 1, 2015 9:51:47 PM\",\"status\":\"verify\",\"articleCount\":25,\"socialUser\":false,\"writerCount\":19,\"followerCount\":1120},{\"userId\":\"2uK\",\"userName\":\"시골살이궁리소\",\"userImage\":\"http://t1.daumcdn.net/brunch/service/user/2uK/image/v-S-Thh_t9R_sFH0dB5DzVFmMa8.jpg\",\"profileId\":\"sigol\",\"description\":\"채상헌교수(연암대학 스마트원예계열 농대창업전공)\",\"createTime\":\"May 18, 2015 5:31:34 PM\",\"status\":\"verify\",\"articleCount\":87,\"socialUser\":false,\"writerCount\":1,\"followerCount\":582},{\"userId\":\"rF3\",\"userName\":\"오쌤\",\"userImage\":\"http://t1.daumcdn.net/brunch/service/user/rF3/image/AX3z3ZpL_jAuCFJ3aQlnxv911T0.jpg\",\"profileId\":\"zavara15\",\"description\":\"단편등단작가. 국어/논술강사\",\"createTime\":\"Sep 12, 2015 1:11:07 PM\",\"status\":\"verify\",\"articleCount\":212,\"socialUser\":false,\"writerCount\":128,\"followerCount\":417},{\"userId\":\"eb0\",\"userName\":\"Lee Daehyun\",\"userImage\":\"http://t1.daumcdn.net/brunch/service/user/eb0/image/BAA8OO0gmqSN9RRz8i4s2esZi0o.png\",\"profileId\":\"leedaehyun\",\"description\":\"\",\"createTime\":\"Aug 5, 2015 3:02:06 PM\",\"status\":\"verify\",\"articleCount\":162,\"socialUser\":false,\"writerCount\":143,\"followerCount\":1435},{\"userId\":\"tLq\",\"userName\":\"연민\",\"userImage\":\"http://t1.daumcdn.net/brunch/service/user/tLq/image/FHg8-Ajy1Cgo_5B_clNAc5QE-eM\",\"profileId\":\"platon1026\",\"description\":\"공부하며 사는 삶,  공부를 공부하다.\",\"createTime\":\"Sep 17, 2015 7:42:32 PM\",\"status\":\"verify\",\"articleCount\":41,\"socialUser\":false,\"writerCount\":2,\"followerCount\":2573},{\"userId\":\"pCo\",\"userName\":\"황병선\",\"userImage\":\"http://t1.daumcdn.net/brunch/service/guest/image/pnhc3CXC3i3zYhegAPlfyNYJ0oU\",\"profileId\":\"marsnine\",\"description\":\"빅뱅엔젤스 대표, 레진코믹스 엔젤투자자, 아카데미X 대표, KAIST S/W대학원 대우교수\",\"createTime\":\"Sep 7, 2015 12:14:46 AM\",\"status\":\"verify\",\"articleCount\":34,\"socialUser\":false,\"writerCount\":5,\"followerCount\":3952},{\"userId\":\"Oyn\",\"userName\":\"류휘\",\"userImage\":\"http://t1.daumcdn.net/brunch/service/user/Oyn/image/VCvVONVuxM3POU5AYJsqXJxy6-Q.jpg\",\"profileId\":\"theteller\",\"description\":\"영화를 보고 책을 읽고, 학교에서 가르칩니다.\",\"createTime\":\"Nov 16, 2015 12:42:24 PM\",\"status\":\"verify\",\"articleCount\":29,\"socialUser\":false,\"writerCount\":13,\"followerCount\":1469},{\"userId\":\"1hkc\",\"userName\":\"윤성민\",\"userImage\":\"http://t1.daumcdn.net/brunch/service/user/1hkc/image/1LYx5DGhl0GLxDIJFwqFZAzP_ow.jpg\",\"profileId\":\"nabodado\",\"description\":\"사진을 좋아하는 초등학교 교사입니다.\",\"createTime\":\"Mar 2, 2016 1:03:08 AM\",\"status\":\"verify\",\"articleCount\":120,\"socialUser\":false,\"writerCount\":64,\"followerCount\":1434},{\"userId\":\"15fL\",\"userName\":\"LC\",\"userImage\":\"http://t1.daumcdn.net/brunch/service/user/15fL/image/MoRPRiJeIUIfZ8YJ8me88YyGxIk.png\",\"profileId\":\"legend\",\"description\":\"| 정장보다 츄리닝 입을 때 옷발이 더 잘 받는다고 믿는 | 보통의 남자 |\\n세계일주 여행자. 젬베 연주자. 서퍼. 그리고 국어쌤이었다. -- Just keep going.\",\"createTime\":\"Jan 14, 2016 6:43:23 PM\",\"status\":\"verify\",\"articleCount\":106,\"socialUser\":false,\"writerCount\":41,\"followerCount\":786},{\"userId\":\"1cre\",\"userName\":\"남성준\",\"userImage\":\"http://t1.daumcdn.net/brunch/service/guest/image/Ik5gMs19yg5jelMhovXMmqgUZZE.png\",\"profileId\":\"sungjoonnam\",\"description\":\"뉴욕, 홍콩에서 바라본 한국의 일자리, 스타트업 정부 정책에 대한 생각들을 나누고 싶습니다. \\n홍콩시립대 방문교수, 유한책임회사 넘버애널리틱스 대표\",\"createTime\":\"Feb 13, 2016 4:15:01 AM\",\"status\":\"verify\",\"articleCount\":9,\"socialUser\":false,\"writerCount\":2,\"followerCount\":3556}],\"title\":\"\\u003cb\\u003e교사\\u003c/b\\u003e 작가\",\"keyword\":\"25\"}","contents":{"profileList":[{"userId":"1cee","userName":"박찬학","userImage":"http://t1.daumcdn.net/brunch/service/guest/image/D0txy0Kh-p10JA6qsBju5nDSeK0","profileId":"tel1638","profileImage":null,"description":"이우학교 역사교사","createTime":1455252786000,"status":"verify","articleCount":88,"socialUser":false,"writerCount":12,"followerCount":1313,"restrictTime":null},{"userId":"2fEJ","userName":"UX 컨설턴트 전민수","userImage":"http://t1.daumcdn.net/brunch/service/user/2fEJ/image/W2jzfbkxN-PnaLqxgR2ydurJLjM.jpg","profileId":"ebprux","profileImage":null,"description":"UX 컨설팅 ·UX리서치 전문 이비피알유엑스(www.ebprux.co.kr) 대표 이사 / UX 컨설팅 및 강의 문의 시 010.4308.7532 문자 주세요","createTime":1470117274000,"status":"verify","articleCount":235,"socialUser":false,"writerCount":9,"followerCount":5966,"restrictTime":null},{"userId":"32mB","userName":"모종린의 골목길 경제학","userImage":"http://t1.daumcdn.net/brunch/service/user/32mB/image/RTNQIStIvk9aAgmIMoL3NZ2uJ5E.jpg","profileId":"riglobalization","profileImage":null,"description":"<작은 도시 큰 기업> 저자\n<라이프스타일 도시> 저자\nwww.facebook.com/jongryn.mo","createTime":1486429995000,"status":"verify","articleCount":21,"socialUser":false,"writerCount":16,"followerCount":1003,"restrictTime":null},{"userId":"kZ6","userName":"천쌤","userImage":"http://t1.daumcdn.net/brunch/service/guest/image/BNeh0ltLFJgBGT87umnfbcxxR_8.png","profileId":"visionary","profileImage":null,"description":"철부지선생님과 아이들 그리고 수학이야기","createTime":1440608345000,"status":"verify","articleCount":10,"socialUser":false,"writerCount":16,"followerCount":38,"restrictTime":null},{"userId":"sJu","userName":"수요일밴드 박대현입니다","userImage":"http://t1.daumcdn.net/brunch/service/guest/image/LMbZOvmuDFJX8KZYyOxO7NsB9wU","profileId":"sooband","profileImage":null,"description":"뭐 하나 제대로 하는 건 없지만 안 하는 건 없습니다.","createTime":1442295750000,"status":"verify","articleCount":252,"socialUser":false,"writerCount":89,"followerCount":1729,"restrictTime":null},{"userId":"38P","userName":"나는일학년담임","userImage":"http://t1.daumcdn.net/brunch/service/user/38P/image/XXw3Rndx1XLI3cyHse8w3cQ0pYc","profileId":"songjh03","profileImage":null,"description":"농촌의 작은 초등학교 1학년 교사입니다. 만 여섯 살 갓 넘은 아이들이 성장하느라 얼마나 애를 쓰는지, 그 노력들이 왜 숭고한지, 성장의 경건함을 보여드리고 싶습","createTime":1434935593000,"status":"verify","articleCount":128,"socialUser":false,"writerCount":43,"followerCount":4007,"restrictTime":null},{"userId":"1eCc","userName":"모순선생","userImage":"http://t1.daumcdn.net/brunch/service/user/1eCc/image/JzrAA4uhSiWu670ygl9Q_Y4K9IE.png","profileId":"hshello","profileImage":null,"description":"교사는 되는 것이 아니라 되어지는 것이다, '티처메카 중등 임용 교육학 논술 강사'","createTime":1455929971000,"status":"verify","articleCount":32,"socialUser":false,"writerCount":26,"followerCount":890,"restrictTime":null},{"userId":"zTK","userName":"호호할멈","userImage":"http://t1.daumcdn.net/brunch/service/guest/image/c1mqW8nXch7NWaaIzbqWGIEhanU.png","profileId":"yooatic84","profileImage":null,"description":"시덥잖은 잡생각을 끝까지 꺼내 \n잡생각에 대한 생각을 정리합니다.","createTime":1443703907000,"status":"verify","articleCount":25,"socialUser":false,"writerCount":19,"followerCount":1120,"restrictTime":null},{"userId":"2uK","userName":"시골살이궁리소","userImage":"http://t1.daumcdn.net/brunch/service/user/2uK/image/v-S-Thh_t9R_sFH0dB5DzVFmMa8.jpg","profileId":"sigol","profileImage":null,"description":"채상헌교수(연암대학 스마트원예계열 농대창업전공)","createTime":1431937894000,"status":"verify","articleCount":87,"socialUser":false,"writerCount":1,"followerCount":582,"restrictTime":null},{"userId":"rF3","userName":"오쌤","userImage":"http://t1.daumcdn.net/brunch/service/user/rF3/image/AX3z3ZpL_jAuCFJ3aQlnxv911T0.jpg","profileId":"zavara15","profileImage":null,"description":"단편등단작가. 국어/논술강사","createTime":1442031067000,"status":"verify","articleCount":212,"socialUser":false,"writerCount":128,"followerCount":417,"restrictTime":null},{"userId":"eb0","userName":"Lee Daehyun","userImage":"http://t1.daumcdn.net/brunch/service/user/eb0/image/BAA8OO0gmqSN9RRz8i4s2esZi0o.png","profileId":"leedaehyun","profileImage":null,"description":"","createTime":1438754526000,"status":"verify","articleCount":162,"socialUser":false,"writerCount":143,"followerCount":1435,"restrictTime":null},{"userId":"tLq","userName":"연민","userImage":"http://t1.daumcdn.net/brunch/service/user/tLq/image/FHg8-Ajy1Cgo_5B_clNAc5QE-eM","profileId":"platon1026","profileImage":null,"description":"공부하며 사는 삶,  공부를 공부하다.","createTime":1442486552000,"status":"verify","articleCount":41,"socialUser":false,"writerCount":2,"followerCount":2573,"restrictTime":null},{"userId":"pCo","userName":"황병선","userImage":"http://t1.daumcdn.net/brunch/service/guest/image/pnhc3CXC3i3zYhegAPlfyNYJ0oU","profileId":"marsnine","profileImage":null,"description":"빅뱅엔젤스 대표, 레진코믹스 엔젤투자자, 아카데미X 대표, KAIST S/W대학원 대우교수","createTime":1441552486000,"status":"verify","articleCount":34,"socialUser":false,"writerCount":5,"followerCount":3952,"restrictTime":null},{"userId":"Oyn","userName":"류휘","userImage":"http://t1.daumcdn.net/brunch/service/user/Oyn/image/VCvVONVuxM3POU5AYJsqXJxy6-Q.jpg","profileId":"theteller","profileImage":null,"description":"영화를 보고 책을 읽고, 학교에서 가르칩니다.","createTime":1447645344000,"status":"verify","articleCount":29,"socialUser":false,"writerCount":13,"followerCount":1469,"restrictTime":null},{"userId":"1hkc","userName":"윤성민","userImage":"http://t1.daumcdn.net/brunch/service/user/1hkc/image/1LYx5DGhl0GLxDIJFwqFZAzP_ow.jpg","profileId":"nabodado","profileImage":null,"description":"사진을 좋아하는 초등학교 교사입니다.","createTime":1456848188000,"status":"verify","articleCount":120,"socialUser":false,"writerCount":64,"followerCount":1434,"restrictTime":null},{"userId":"15fL","userName":"LC","userImage":"http://t1.daumcdn.net/brunch/service/user/15fL/image/MoRPRiJeIUIfZ8YJ8me88YyGxIk.png","profileId":"legend","profileImage":null,"description":"| 정장보다 츄리닝 입을 때 옷발이 더 잘 받는다고 믿는 | 보통의 남자 |\n세계일주 여행자. 젬베 연주자. 서퍼. 그리고 국어쌤이었다. -- Just keep going.","createTime":1452764603000,"status":"verify","articleCount":106,"socialUser":false,"writerCount":41,"followerCount":786,"restrictTime":null},{"userId":"1cre","userName":"남성준","userImage":"http://t1.daumcdn.net/brunch/service/guest/image/Ik5gMs19yg5jelMhovXMmqgUZZE.png","profileId":"sungjoonnam","profileImage":null,"description":"뉴욕, 홍콩에서 바라본 한국의 일자리, 스타트업 정부 정책에 대한 생각들을 나누고 싶습니다. \n홍콩시립대 방문교수, 유한책임회사 넘버애널리틱스 대표","createTime":1455304501000,"status":"verify","articleCount":9,"socialUser":false,"writerCount":2,"followerCount":3556,"restrictTime":null}],"title":"<b>교사</b> 작가","keyword":"25"},"createTime":null,"seq":13,"setNo":0},{"no":3527,"type":"KEYWORD_ARTICLE_AUTO","active":false,"deploy":false,"data":"{\"htmlKeywordTitle\":\"\\u003cb\\u003e문화\\u003c/b\\u003e·\\u003cb\\u003e예술\\u003c/b\\u003e\",\"keywordTitle\":\"문화·예술\",\"groupNo\":64,\"groupType\":\"group\",\"list\":[]}","contents":{"keyword":null,"htmlKeywordTitle":"<b>문화</b>·<b>예술</b>","keywordTitle":"문화·예술","moreLink":null,"groupNo":64,"groupType":"group","list":[]},"createTime":null,"seq":14,"setNo":0},{"no":3528,"type":"KEYWORD_ARTICLE_AUTO","active":false,"deploy":false,"data":"{\"htmlKeywordTitle\":\"\\u003cb\\u003e교육\\u003c/b\\u003e 이야기\",\"keywordTitle\":\"교육 이야기\",\"groupNo\":70,\"groupType\":\"group\",\"list\":[]}","contents":{"keyword":null,"htmlKeywordTitle":"<b>교육</b> 이야기","keywordTitle":"교육 이야기","moreLink":null,"groupNo":70,"groupType":"group","list":[]},"createTime":null,"seq":15,"setNo":0},{"no":3529,"type":"KEYWORD_ARTICLE_AUTO","active":false,"deploy":false,"data":"{\"htmlKeywordTitle\":\"직장인 \\u003cb\\u003e자기계발\\u003c/b\\u003e\",\"keywordTitle\":\"직장인 자기계발\",\"groupNo\":65,\"groupType\":\"group\",\"list\":[]}","contents":{"keyword":null,"htmlKeywordTitle":"직장인 <b>자기계발</b>","keywordTitle":"직장인 자기계발","moreLink":null,"groupNo":65,"groupType":"group","list":[]},"createTime":null,"seq":16,"setNo":0},{"no":3530,"type":"KEYWORD_USER","active":false,"deploy":false,"data":"{\"profileList\":[{\"userId\":\"36B\",\"userName\":\"현정 Lee\",\"userImage\":\"http://t1.daumcdn.net/brunch/service/user/36B/image/2opTfUP5YONpyMil5pY60L3toWA.png\",\"profileId\":\"cloudy\",\"description\":\"나는 눈물이 없는 사람을 사랑하지 않는다.\",\"createTime\":\"Jun 22, 2015 3:47:03 AM\",\"status\":\"verify\",\"articleCount\":72,\"socialUser\":false,\"writerCount\":40,\"followerCount\":208},{\"userId\":\"17XH\",\"userName\":\"예또\",\"userImage\":\"http://t1.daumcdn.net/brunch/service/guest/image/8lpxU2r96yFl7JtrLP-7eKAyuog.png\",\"profileId\":\"netsgo0319\",\"description\":\"어른의 사춘기를 겪으며\",\"createTime\":\"Jan 24, 2016 11:20:13 PM\",\"status\":\"verify\",\"articleCount\":41,\"socialUser\":false,\"writerCount\":132,\"followerCount\":2432},{\"userId\":\"Ijp\",\"userName\":\"만땅소울\",\"userImage\":\"http://t1.daumcdn.net/brunch/service/user/Ijp/image/e87YDlnaquuYepgXBNdzJAphikw.png\",\"profileId\":\"themusiq\",\"description\":\"음악, 디자인, 사진, 여행을 좋아하는 자발적 칼럼니스트입니다.\",\"createTime\":\"Oct 25, 2015 2:54:34 PM\",\"status\":\"verify\",\"articleCount\":364,\"socialUser\":false,\"writerCount\":78,\"followerCount\":1178},{\"userId\":\"AyC\",\"userName\":\"천미르\",\"userImage\":\"http://t1.daumcdn.net/brunch/service/user/AyC/image/QERr-cuCMotjPrvI2RGXCJyeN70.jpg\",\"profileId\":\"1000ml\",\"description\":\"1000mL 가득 담긴 팝 이야기.\",\"createTime\":\"Oct 2, 2015 11:26:46 PM\",\"status\":\"verify\",\"articleCount\":82,\"socialUser\":false,\"writerCount\":9,\"followerCount\":244},{\"userId\":\"3B5\",\"userName\":\"박재우\",\"userImage\":\"http://t1.daumcdn.net/brunch/service/guest/image/Cx_Jo6dAtcjplaQw-f8Q1PgN3Js.png\",\"profileId\":\"4indie\",\"description\":\"보고 들은 것들에 색깔을 칠합니다.\\n이메일: 4indie@naver.com\\n카카오톡 ID: 4indie\",\"createTime\":\"Jun 23, 2015 3:30:38 PM\",\"status\":\"verify\",\"articleCount\":258,\"socialUser\":false,\"writerCount\":55,\"followerCount\":982},{\"userId\":\"iHR\",\"userName\":\"Connect Art\",\"userImage\":\"http://t1.daumcdn.net/brunch/service/user/iHR/image/PNhwXe1HOKKgPcBxw8aibkGNtqg\",\"profileId\":\"connectart\",\"description\":\"그림 그리고 글 쓰는 바이올리니스트 이수민입니다.\",\"createTime\":\"Aug 20, 2015 1:13:17 AM\",\"status\":\"verify\",\"articleCount\":39,\"socialUser\":false,\"writerCount\":15,\"followerCount\":1663},{\"userId\":\"5m4\",\"userName\":\"DancingDean\",\"userImage\":\"http://t1.daumcdn.net/brunch/service/user/5m4/image/3kJVmJxSbrKq8k_j-fjiYM2QuLI.jpeg\",\"profileId\":\"deankim\",\"description\":\"#BRANDizer #DSTrue_대성진리교 #PAC #AMA  #PlanM #세이테니스 #레디언스3루수 #뼈두맨  #NO꼰대canSavetheEarth\",\"createTime\":\"Jul 1, 2015 4:38:52 PM\",\"status\":\"verify\",\"articleCount\":26,\"socialUser\":false,\"writerCount\":67,\"followerCount\":52},{\"userId\":\"aY5\",\"userName\":\"Aprilamb\",\"userImage\":\"http://t1.daumcdn.net/brunch/service/user/aY5/image/jBiDL5o7knGPZkYpdydzYFvC5oY\",\"profileId\":\"doubleshot\",\"description\":\"\\u0027사월의 양\\u0027입니다. 샌프란시스코에 거주하면서 여행기 보다는 생활기에 가까운 에세이들을 포스팅하다가 다시 서울로 돌아와서...\",\"createTime\":\"Jul 24, 2015 12:56:24 AM\",\"status\":\"verify\",\"articleCount\":264,\"socialUser\":false,\"writerCount\":60,\"followerCount\":521},{\"userId\":\"4dw\",\"userName\":\"서비스 디자이너의 음악 감상실\",\"userImage\":\"http://t1.daumcdn.net/brunch/service/user/4dw/image/H_WnbJpAl5vbPnhKrnnfNW3ktCI\",\"profileId\":\"makecake\",\"description\":\"음악을 공유하는 서비스 디자이너\",\"createTime\":\"Jun 27, 2015 12:39:36 AM\",\"status\":\"verify\",\"articleCount\":53,\"socialUser\":false,\"writerCount\":11,\"followerCount\":2056},{\"userId\":\"3WM\",\"userName\":\"김성대\",\"userImage\":\"http://t1.daumcdn.net/brunch/service/user/3WM/image/EIdqAmyz_7wfozota5dHf1vxZYA.jpg\",\"profileId\":\"acdcrock\",\"description\":\"한국대중음악상선정위원\\n마이데일리 김성대의 음악노트\\n네이버뮤직 이주의 발견(국내)/파라노이드(Paranoid)/음악취향Y/그루버스(groovers+) 필진\",\"createTime\":\"Jun 25, 2015 10:26:55 AM\",\"status\":\"verify\",\"articleCount\":199,\"socialUser\":false,\"writerCount\":0,\"followerCount\":844}],\"title\":\"\\u003cb\\u003e음악\\u003c/b\\u003e 작가\",\"keyword\":\"19\"}","contents":{"profileList":[{"userId":"36B","userName":"현정 Lee","userImage":"http://t1.daumcdn.net/brunch/service/user/36B/image/2opTfUP5YONpyMil5pY60L3toWA.png","profileId":"cloudy","profileImage":null,"description":"나는 눈물이 없는 사람을 사랑하지 않는다.","createTime":1434912423000,"status":"verify","articleCount":72,"socialUser":false,"writerCount":40,"followerCount":208,"restrictTime":null},{"userId":"17XH","userName":"예또","userImage":"http://t1.daumcdn.net/brunch/service/guest/image/8lpxU2r96yFl7JtrLP-7eKAyuog.png","profileId":"netsgo0319","profileImage":null,"description":"어른의 사춘기를 겪으며","createTime":1453645213000,"status":"verify","articleCount":41,"socialUser":false,"writerCount":132,"followerCount":2432,"restrictTime":null},{"userId":"Ijp","userName":"만땅소울","userImage":"http://t1.daumcdn.net/brunch/service/user/Ijp/image/e87YDlnaquuYepgXBNdzJAphikw.png","profileId":"themusiq","profileImage":null,"description":"음악, 디자인, 사진, 여행을 좋아하는 자발적 칼럼니스트입니다.","createTime":1445752474000,"status":"verify","articleCount":364,"socialUser":false,"writerCount":78,"followerCount":1178,"restrictTime":null},{"userId":"AyC","userName":"천미르","userImage":"http://t1.daumcdn.net/brunch/service/user/AyC/image/QERr-cuCMotjPrvI2RGXCJyeN70.jpg","profileId":"1000ml","profileImage":null,"description":"1000mL 가득 담긴 팝 이야기.","createTime":1443796006000,"status":"verify","articleCount":82,"socialUser":false,"writerCount":9,"followerCount":244,"restrictTime":null},{"userId":"3B5","userName":"박재우","userImage":"http://t1.daumcdn.net/brunch/service/guest/image/Cx_Jo6dAtcjplaQw-f8Q1PgN3Js.png","profileId":"4indie","profileImage":null,"description":"보고 들은 것들에 색깔을 칠합니다.\n이메일: 4indie@naver.com\n카카오톡 ID: 4indie","createTime":1435041038000,"status":"verify","articleCount":258,"socialUser":false,"writerCount":55,"followerCount":982,"restrictTime":null},{"userId":"iHR","userName":"Connect Art","userImage":"http://t1.daumcdn.net/brunch/service/user/iHR/image/PNhwXe1HOKKgPcBxw8aibkGNtqg","profileId":"connectart","profileImage":null,"description":"그림 그리고 글 쓰는 바이올리니스트 이수민입니다.","createTime":1440000797000,"status":"verify","articleCount":39,"socialUser":false,"writerCount":15,"followerCount":1663,"restrictTime":null},{"userId":"5m4","userName":"DancingDean","userImage":"http://t1.daumcdn.net/brunch/service/user/5m4/image/3kJVmJxSbrKq8k_j-fjiYM2QuLI.jpeg","profileId":"deankim","profileImage":null,"description":"#BRANDizer #DSTrue_대성진리교 #PAC #AMA  #PlanM #세이테니스 #레디언스3루수 #뼈두맨  #NO꼰대canSavetheEarth","createTime":1435736332000,"status":"verify","articleCount":26,"socialUser":false,"writerCount":67,"followerCount":52,"restrictTime":null},{"userId":"aY5","userName":"Aprilamb","userImage":"http://t1.daumcdn.net/brunch/service/user/aY5/image/jBiDL5o7knGPZkYpdydzYFvC5oY","profileId":"doubleshot","profileImage":null,"description":"'사월의 양'입니다. 샌프란시스코에 거주하면서 여행기 보다는 생활기에 가까운 에세이들을 포스팅하다가 다시 서울로 돌아와서...","createTime":1437666984000,"status":"verify","articleCount":264,"socialUser":false,"writerCount":60,"followerCount":521,"restrictTime":null},{"userId":"4dw","userName":"서비스 디자이너의 음악 감상실","userImage":"http://t1.daumcdn.net/brunch/service/user/4dw/image/H_WnbJpAl5vbPnhKrnnfNW3ktCI","profileId":"makecake","profileImage":null,"description":"음악을 공유하는 서비스 디자이너","createTime":1435333176000,"status":"verify","articleCount":53,"socialUser":false,"writerCount":11,"followerCount":2056,"restrictTime":null},{"userId":"3WM","userName":"김성대","userImage":"http://t1.daumcdn.net/brunch/service/user/3WM/image/EIdqAmyz_7wfozota5dHf1vxZYA.jpg","profileId":"acdcrock","profileImage":null,"description":"한국대중음악상선정위원\n마이데일리 김성대의 음악노트\n네이버뮤직 이주의 발견(국내)/파라노이드(Paranoid)/음악취향Y/그루버스(groovers+) 필진","createTime":1435195615000,"status":"verify","articleCount":199,"socialUser":false,"writerCount":0,"followerCount":844,"restrictTime":null}],"title":"<b>음악</b> 작가","keyword":"19"},"createTime":null,"seq":17,"setNo":0},{"no":3531,"type":"KEYWORD_BRUNCH_RECENT","active":false,"deploy":false,"data":null,"contents":null,"createTime":null,"seq":18,"setNo":0},{"no":3532,"type":"KEYWORD_POPULAR","active":false,"deploy":false,"data":"{\"keywordItemList\":[{\"no\":1689,\"id\":1689,\"keyword\":\"사진\",\"score\":0,\"count\":1},{\"no\":1501,\"id\":1501,\"keyword\":\"벚꽃\",\"score\":0,\"count\":1},{\"no\":1386,\"id\":1386,\"keyword\":\"미국\",\"score\":0,\"count\":1},{\"no\":2032,\"id\":2032,\"keyword\":\"시간\",\"score\":0,\"count\":1},{\"no\":1549,\"id\":1549,\"keyword\":\"봄\",\"score\":0,\"count\":1},{\"no\":2446,\"id\":2446,\"keyword\":\"외로움\",\"score\":0,\"count\":1},{\"no\":1880,\"id\":1880,\"keyword\":\"소설\",\"score\":0,\"count\":1},{\"no\":3547,\"id\":3547,\"keyword\":\"행복\",\"score\":0,\"count\":1},{\"no\":1851,\"id\":1851,\"keyword\":\"세월호\",\"score\":0,\"count\":1},{\"no\":2989,\"id\":2989,\"keyword\":\"책\",\"score\":0,\"count\":1}]}","contents":{"keywordItemList":[{"no":1689,"id":1689,"onoff":null,"keyword":"사진","type":null,"score":0,"updateTime":null,"createTime":null,"source":null,"agentId":null,"bannerOnoff":null,"pcImageUrl":null,"pcImageLink":null,"pcBackgroundColor":null,"pcTextImage":null,"mobileImageUrl":null,"mobileImageLink":null,"mobileBackgroundColor":null,"mobileTextImage":null,"selected":null,"count":1,"orderType":null,"finalScore":0.0},{"no":1501,"id":1501,"onoff":null,"keyword":"벚꽃","type":null,"score":0,"updateTime":null,"createTime":null,"source":null,"agentId":null,"bannerOnoff":null,"pcImageUrl":null,"pcImageLink":null,"pcBackgroundColor":null,"pcTextImage":null,"mobileImageUrl":null,"mobileImageLink":null,"mobileBackgroundColor":null,"mobileTextImage":null,"selected":null,"count":1,"orderType":null,"finalScore":0.0},{"no":1386,"id":1386,"onoff":null,"keyword":"미국","type":null,"score":0,"updateTime":null,"createTime":null,"source":null,"agentId":null,"bannerOnoff":null,"pcImageUrl":null,"pcImageLink":null,"pcBackgroundColor":null,"pcTextImage":null,"mobileImageUrl":null,"mobileImageLink":null,"mobileBackgroundColor":null,"mobileTextImage":null,"selected":null,"count":1,"orderType":null,"finalScore":0.0},{"no":2032,"id":2032,"onoff":null,"keyword":"시간","type":null,"score":0,"updateTime":null,"createTime":null,"source":null,"agentId":null,"bannerOnoff":null,"pcImageUrl":null,"pcImageLink":null,"pcBackgroundColor":null,"pcTextImage":null,"mobileImageUrl":null,"mobileImageLink":null,"mobileBackgroundColor":null,"mobileTextImage":null,"selected":null,"count":1,"orderType":null,"finalScore":0.0},{"no":1549,"id":1549,"onoff":null,"keyword":"봄","type":null,"score":0,"updateTime":null,"createTime":null,"source":null,"agentId":null,"bannerOnoff":null,"pcImageUrl":null,"pcImageLink":null,"pcBackgroundColor":null,"pcTextImage":null,"mobileImageUrl":null,"mobileImageLink":null,"mobileBackgroundColor":null,"mobileTextImage":null,"selected":null,"count":1,"orderType":null,"finalScore":0.0},{"no":2446,"id":2446,"onoff":null,"keyword":"외로움","type":null,"score":0,"updateTime":null,"createTime":null,"source":null,"agentId":null,"bannerOnoff":null,"pcImageUrl":null,"pcImageLink":null,"pcBackgroundColor":null,"pcTextImage":null,"mobileImageUrl":null,"mobileImageLink":null,"mobileBackgroundColor":null,"mobileTextImage":null,"selected":null,"count":1,"orderType":null,"finalScore":0.0},{"no":1880,"id":1880,"onoff":null,"keyword":"소설","type":null,"score":0,"updateTime":null,"createTime":null,"source":null,"agentId":null,"bannerOnoff":null,"pcImageUrl":null,"pcImageLink":null,"pcBackgroundColor":null,"pcTextImage":null,"mobileImageUrl":null,"mobileImageLink":null,"mobileBackgroundColor":null,"mobileTextImage":null,"selected":null,"count":1,"orderType":null,"finalScore":0.0},{"no":3547,"id":3547,"onoff":null,"keyword":"행복","type":null,"score":0,"updateTime":null,"createTime":null,"source":null,"agentId":null,"bannerOnoff":null,"pcImageUrl":null,"pcImageLink":null,"pcBackgroundColor":null,"pcTextImage":null,"mobileImageUrl":null,"mobileImageLink":null,"mobileBackgroundColor":null,"mobileTextImage":null,"selected":null,"count":1,"orderType":null,"finalScore":0.0},{"no":1851,"id":1851,"onoff":null,"keyword":"세월호","type":null,"score":0,"updateTime":null,"createTime":null,"source":null,"agentId":null,"bannerOnoff":null,"pcImageUrl":null,"pcImageLink":null,"pcBackgroundColor":null,"pcTextImage":null,"mobileImageUrl":null,"mobileImageLink":null,"mobileBackgroundColor":null,"mobileTextImage":null,"selected":null,"count":1,"orderType":null,"finalScore":0.0},{"no":2989,"id":2989,"onoff":null,"keyword":"책","type":null,"score":0,"updateTime":null,"createTime":null,"source":null,"agentId":null,"bannerOnoff":null,"pcImageUrl":null,"pcImageLink":null,"pcBackgroundColor":null,"pcTextImage":null,"mobileImageUrl":null,"mobileImageLink":null,"mobileBackgroundColor":null,"mobileTextImage":null,"selected":null,"count":1,"orderType":null,"finalScore":0.0}]},"createTime":null,"seq":19,"setNo":0}]}}